[
  {
    "PlayerID":2428,
    "SeasonType":1,
    "Season":2016,
    "Team":"ARI",
    "Number":3,
    "Name":"Carson Palmer",
    "Position":"QB",
    "PositionCategory":"OFF",
    "Activated":15,
    "Played":15,
    "Started":15,
    "PassingAttempts":153.00,
    "PassingCompletions":94.00,
    "PassingYards":997.00,
    "PassingCompletionPercentage":61.4,
    "PassingYardsPerAttempt":6.5,
    "PassingYardsPerCompletion":10.6,
    "PassingTouchdowns":9.00,
    "PassingInterceptions":6.00,
    "PassingRating":83.70,
    "PassingLong":40.00,
    "PassingSacks":12.00,
    "PassingSackYards":87.00,
    "RushingAttempts":3.00,
    "RushingYards":8.00,
    "RushingYardsPerAttempt":2.7,
    "RushingTouchdowns":0.00,
    "RushingLong":16.00,
    "ReceivingTargets":0.00,
    "Receptions":0.00,
    "ReceivingYards":0.00,
    "ReceivingYardsPerReception":0,
    "ReceivingTouchdowns":0.00,
    "ReceivingLong":0.00,
    "Fumbles":5.00,
    "FumblesLost":2.00,
    "PuntReturns":0.00,
    "PuntReturnYards":0.00,
    "PuntReturnYardsPerAttempt":0,
    "PuntReturnTouchdowns":0.00,
    "PuntReturnLong":0.00,
    "KickReturns":0.00,
    "KickReturnYards":0.00,
    "KickReturnYardsPerAttempt":0,
    "KickReturnTouchdowns":0.00,
    "KickReturnLong":0.00,
    "SoloTackles":0.00,
    "AssistedTackles":0.00,
    "TacklesForLoss":0.00,
    "Sacks":0.00,
    "SackYards":0.00,
    "QuarterbackHits":0.00,
    "PassesDefended":0.00,
    "FumblesForced":0.00,
    "FumblesRecovered":1.00,
    "FumbleReturnYards":0.00,
    "FumbleReturnTouchdowns":0.00,
    "Interceptions":0.00,
    "InterceptionReturnYards":0.00,
    "InterceptionReturnTouchdowns":0.00,
    "BlockedKicks":0.00,
    "SpecialTeamsSoloTackles":0.00,
    "SpecialTeamsAssistedTackles":0.00,
    "MiscSoloTackles":0.00,
    "MiscAssistedTackles":0.00,
    "Punts":0.00,
    "PuntYards":0.00,
    "PuntAverage":0,
    "FieldGoalsAttempted":0.00,
    "FieldGoalsMade":0.00,
    "FieldGoalsLongestMade":0.00,
    "ExtraPointsMade":0.00,
    "TwoPointConversionPasses":0.00,
    "TwoPointConversionRuns":0.00,
    "TwoPointConversionReceptions":0.00,
    "FantasyPoints":60.68,
    "FantasyPointsPPR":60.68,
    "ReceptionPercentage":0,
    "ReceivingYardsPerTarget":0,
    "Tackles":0,
    "OffensiveTouchdowns":0,
    "DefensiveTouchdowns":0,
    "SpecialTeamsTouchdowns":0,
    "Touchdowns":0,
    "FantasyPosition":"QB",
    "FieldGoalPercentage":0,
    "PlayerSeasonID":15524463,
    "FumblesOwnRecoveries":0.00,
    "FumblesOutOfBounds":0.00,
    "KickReturnFairCatches":0.00,
    "PuntReturnFairCatches":0.00,
    "PuntTouchbacks":0.00,
    "PuntInside20":0.00,
    "PuntNetAverage":0,
    "ExtraPointsAttempted":0.00,
    "BlockedKickReturnTouchdowns":0.00,
    "FieldGoalReturnTouchdowns":0.00,
    "Safeties":0.00,
    "FieldGoalsHadBlocked":0.00,
    "PuntsHadBlocked":0.00,
    "ExtraPointsHadBlocked":0.00,
    "PuntLong":0.00,
    "BlockedKickReturnYards":0.00,
    "FieldGoalReturnYards":0.00,
    "PuntNetYards":0.00,
    "SpecialTeamsFumblesForced":0.00,
    "SpecialTeamsFumblesRecovered":0.00,
    "MiscFumblesForced":0.00,
    "MiscFumblesRecovered":0.00,
    "ShortName":"Carson Palmer",
    "SafetiesAllowed":0.00,
    "Temperature":71,
    "Humidity":47,
    "WindSpeed":3,
    "OffensiveSnapsPlayed":null,
    "DefensiveSnapsPlayed":null,
    "SpecialTeamsSnapsPlayed":null,
    "OffensiveTeamSnaps":226,
    "DefensiveTeamSnaps":null,
    "SpecialTeamsTeamSnaps":null,
    "AuctionValue":null,
    "AuctionValuePPR":null,
    "TwoPointConversionReturns":0.00,
    "FantasyPointsFanDuel":66.68,
    "FieldGoalsMade0to19":0.00,
    "FieldGoalsMade20to29":0.00,
    "FieldGoalsMade30to39":0.00,
    "FieldGoalsMade40to49":0.00,
    "FieldGoalsMade50Plus":0.00,
    "FantasyPointsDraftKings":68.68,
    "FantasyPointsYahoo":66.68,
    "AverageDraftPosition":null,
    "AverageDraftPositionPPR":null,
    "TeamID":1,
    "GlobalTeamID":1,
    "FantasyPointsFantasyDraft":68.68
  },
  {
    "PlayerID":15037,
    "SeasonType":1,
    "Season":2016,
    "Team":"ARI",
    "Number":4,
    "Name":"Zac Dysert",
    "Position":"QB",
    "PositionCategory":"OFF",
    "Activated":1,
    "Played":0,
    "Started":0,
    "PassingAttempts":0.00,
    "PassingCompletions":0.00,
    "PassingYards":0.00,
    "PassingCompletionPercentage":0,
    "PassingYardsPerAttempt":0,
    "PassingYardsPerCompletion":0,
    "PassingTouchdowns":0.00,
    "PassingInterceptions":0.00,
    "PassingRating":0,
    "PassingLong":null,
    "PassingSacks":0.00,
    "PassingSackYards":0.00,
    "RushingAttempts":0.00,
    "RushingYards":0.00,
    "RushingYardsPerAttempt":0,
    "RushingTouchdowns":0.00,
    "RushingLong":null,
    "ReceivingTargets":0.00,
    "Receptions":0.00,
    "ReceivingYards":0.00,
    "ReceivingYardsPerReception":0,
    "ReceivingTouchdowns":0.00,
    "ReceivingLong":null,
    "Fumbles":0.00,
    "FumblesLost":0.00,
    "PuntReturns":0.00,
    "PuntReturnYards":0.00,
    "PuntReturnYardsPerAttempt":0,
    "PuntReturnTouchdowns":0.00,
    "PuntReturnLong":null,
    "KickReturns":0.00,
    "KickReturnYards":0.00,
    "KickReturnYardsPerAttempt":0,
    "KickReturnTouchdowns":0.00,
    "KickReturnLong":null,
    "SoloTackles":0.00,
    "AssistedTackles":0.00,
    "TacklesForLoss":0.00,
    "Sacks":0.00,
    "SackYards":0.00,
    "QuarterbackHits":0.00,
    "PassesDefended":0.00,
    "FumblesForced":0.00,
    "FumblesRecovered":0.00,
    "FumbleReturnYards":0.00,
    "FumbleReturnTouchdowns":0.00,
    "Interceptions":0.00,
    "InterceptionReturnYards":0.00,
    "InterceptionReturnTouchdowns":0.00,
    "BlockedKicks":0.00,
    "SpecialTeamsSoloTackles":0.00,
    "SpecialTeamsAssistedTackles":0.00,
    "MiscSoloTackles":0.00,
    "MiscAssistedTackles":0.00,
    "Punts":0.00,
    "PuntYards":0.00,
    "PuntAverage":0,
    "FieldGoalsAttempted":0.00,
    "FieldGoalsMade":0.00,
    "FieldGoalsLongestMade":null,
    "ExtraPointsMade":0.00,
    "TwoPointConversionPasses":0.00,
    "TwoPointConversionRuns":0.00,
    "TwoPointConversionReceptions":0.00,
    "FantasyPoints":0.00,
    "FantasyPointsPPR":0.00,
    "ReceptionPercentage":0,
    "ReceivingYardsPerTarget":0,
    "Tackles":0,
    "OffensiveTouchdowns":0,
    "DefensiveTouchdowns":0,
    "SpecialTeamsTouchdowns":0,
    "Touchdowns":0,
    "FantasyPosition":"QB",
    "FieldGoalPercentage":0,
    "PlayerSeasonID":162025881,
    "FumblesOwnRecoveries":0.00,
    "FumblesOutOfBounds":0.00,
    "KickReturnFairCatches":0.00,
    "PuntReturnFairCatches":0.00,
    "PuntTouchbacks":0.00,
    "PuntInside20":0.00,
    "PuntNetAverage":0,
    "ExtraPointsAttempted":0.00,
    "BlockedKickReturnTouchdowns":0.00,
    "FieldGoalReturnTouchdowns":0.00,
    "Safeties":0.00,
    "FieldGoalsHadBlocked":0.00,
    "PuntsHadBlocked":0.00,
    "ExtraPointsHadBlocked":0.00,
    "PuntLong":null,
    "BlockedKickReturnYards":0.00,
    "FieldGoalReturnYards":0.00,
    "PuntNetYards":0.00,
    "SpecialTeamsFumblesForced":0.00,
    "SpecialTeamsFumblesRecovered":0.00,
    "MiscFumblesForced":0.00,
    "MiscFumblesRecovered":0.00,
    "ShortName":"Zac Dysert",
    "SafetiesAllowed":0.00,
    "Temperature":75,
    "Humidity":34,
    "WindSpeed":16,
    "OffensiveSnapsPlayed":null,
    "DefensiveSnapsPlayed":null,
    "SpecialTeamsSnapsPlayed":null,
    "OffensiveTeamSnaps":226,
    "DefensiveTeamSnaps":null,
    "SpecialTeamsTeamSnaps":null,
    "AuctionValue":null,
    "AuctionValuePPR":null,
    "TwoPointConversionReturns":0.00,
    "FantasyPointsFanDuel":0.00,
    "FieldGoalsMade0to19":0.00,
    "FieldGoalsMade20to29":0.00,
    "FieldGoalsMade30to39":0.00,
    "FieldGoalsMade40to49":0.00,
    "FieldGoalsMade50Plus":0.00,
    "FantasyPointsDraftKings":0.00,
    "FantasyPointsYahoo":0.00,
    "AverageDraftPosition":null,
    "AverageDraftPositionPPR":null,
    "TeamID":1,
    "GlobalTeamID":1,
    "FantasyPointsFantasyDraft":0.00
  },
  {
    "PlayerID":4737,
    "SeasonType":1,
    "Season":2016,
    "Team":"ARI",
    "Number":5,
    "Name":"Drew Stanton",
    "Position":"QB",
    "PositionCategory":"OFF",
    "Activated":16,
    "Played":5,
    "Started":1,
    "PassingAttempts":18.00,
    "PassingCompletions":5.00,
    "PassingYards":57.00,
    "PassingCompletionPercentage":27.8,
    "PassingYardsPerAttempt":3.2,
    "PassingYardsPerCompletion":11.4,
    "PassingTouchdowns":0.00,
    "PassingInterceptions":1.00,
    "PassingRating":17.13,
    "PassingLong":21.00,
    "PassingSacks":0.00,
    "PassingSackYards":0.00,
    "RushingAttempts":0.00,
    "RushingYards":0.00,
    "RushingYardsPerAttempt":0,
    "RushingTouchdowns":0.00,
    "RushingLong":0.00,
    "ReceivingTargets":0.00,
    "Receptions":0.00,
    "ReceivingYards":0.00,
    "ReceivingYardsPerReception":0,
    "ReceivingTouchdowns":0.00,
    "ReceivingLong":0.00,
    "Fumbles":0.00,
    "FumblesLost":0.00,
    "PuntReturns":0.00,
    "PuntReturnYards":0.00,
    "PuntReturnYardsPerAttempt":0,
    "PuntReturnTouchdowns":0.00,
    "PuntReturnLong":0.00,
    "KickReturns":0.00,
    "KickReturnYards":0.00,
    "KickReturnYardsPerAttempt":0,
    "KickReturnTouchdowns":0.00,
    "KickReturnLong":0.00,
    "SoloTackles":0.00,
    "AssistedTackles":0.00,
    "TacklesForLoss":0.00,
    "Sacks":0.00,
    "SackYards":0.00,
    "QuarterbackHits":0.00,
    "PassesDefended":0.00,
    "FumblesForced":0.00,
    "FumblesRecovered":0.00,
    "FumbleReturnYards":0.00,
    "FumbleReturnTouchdowns":0.00,
    "Interceptions":0.00,
    "InterceptionReturnYards":0.00,
    "InterceptionReturnTouchdowns":0.00,
    "BlockedKicks":0.00,
    "SpecialTeamsSoloTackles":0.00,
    "SpecialTeamsAssistedTackles":0.00,
    "MiscSoloTackles":0.00,
    "MiscAssistedTackles":0.00,
    "Punts":0.00,
    "PuntYards":0.00,
    "PuntAverage":0,
    "FieldGoalsAttempted":0.00,
    "FieldGoalsMade":0.00,
    "FieldGoalsLongestMade":0.00,
    "ExtraPointsMade":0.00,
    "TwoPointConversionPasses":0.00,
    "TwoPointConversionRuns":0.00,
    "TwoPointConversionReceptions":0.00,
    "FantasyPoints":0.28,
    "FantasyPointsPPR":0.28,
    "ReceptionPercentage":0,
    "ReceivingYardsPerTarget":0,
    "Tackles":0,
    "OffensiveTouchdowns":0,
    "DefensiveTouchdowns":0,
    "SpecialTeamsTouchdowns":0,
    "Touchdowns":0,
    "FantasyPosition":"QB",
    "FieldGoalPercentage":0,
    "PlayerSeasonID":15524508,
    "FumblesOwnRecoveries":0.00,
    "FumblesOutOfBounds":0.00,
    "KickReturnFairCatches":0.00,
    "PuntReturnFairCatches":0.00,
    "PuntTouchbacks":0.00,
    "PuntInside20":0.00,
    "PuntNetAverage":0,
    "ExtraPointsAttempted":0.00,
    "BlockedKickReturnTouchdowns":0.00,
    "FieldGoalReturnTouchdowns":0.00,
    "Safeties":0.00,
    "FieldGoalsHadBlocked":0.00,
    "PuntsHadBlocked":0.00,
    "ExtraPointsHadBlocked":0.00,
    "PuntLong":0.00,
    "BlockedKickReturnYards":0.00,
    "FieldGoalReturnYards":0.00,
    "PuntNetYards":0.00,
    "SpecialTeamsFumblesForced":0.00,
    "SpecialTeamsFumblesRecovered":0.00,
    "MiscFumblesForced":0.00,
    "MiscFumblesRecovered":0.00,
    "ShortName":"Drew Stanton",
    "SafetiesAllowed":0.00,
    "Temperature":71,
    "Humidity":47,
    "WindSpeed":3,
    "OffensiveSnapsPlayed":null,
    "DefensiveSnapsPlayed":null,
    "SpecialTeamsSnapsPlayed":null,
    "OffensiveTeamSnaps":226,
    "DefensiveTeamSnaps":null,
    "SpecialTeamsTeamSnaps":null,
    "AuctionValue":null,
    "AuctionValuePPR":null,
    "TwoPointConversionReturns":0.00,
    "FantasyPointsFanDuel":1.28,
    "FieldGoalsMade0to19":0.00,
    "FieldGoalsMade20to29":0.00,
    "FieldGoalsMade30to39":0.00,
    "FieldGoalsMade40to49":0.00,
    "FieldGoalsMade50Plus":0.00,
    "FantasyPointsDraftKings":1.28,
    "FantasyPointsYahoo":1.28,
    "AverageDraftPosition":null,
    "AverageDraftPositionPPR":null,
    "TeamID":1,
    "GlobalTeamID":1,
    "FantasyPointsFantasyDraft":1.28
  },
  {
    "PlayerID":15725,
    "SeasonType":1,
    "Season":2016,
    "Team":"ARI",
    "Number":10,
    "Name":"Brittan Golden",
    "Position":"WR",
    "PositionCategory":"OFF",
    "Activated":12,
    "Played":12,
    "Started":1,
    "PassingAttempts":0.00,
    "PassingCompletions":0.00,
    "PassingYards":0.00,
    "PassingCompletionPercentage":0,
    "PassingYardsPerAttempt":0,
    "PassingYardsPerCompletion":0,
    "PassingTouchdowns":0.00,
    "PassingInterceptions":0.00,
    "PassingRating":0,
    "PassingLong":0.00,
    "PassingSacks":0.00,
    "PassingSackYards":0.00,
    "RushingAttempts":0.00,
    "RushingYards":0.00,
    "RushingYardsPerAttempt":0,
    "RushingTouchdowns":0.00,
    "RushingLong":0.00,
    "ReceivingTargets":5.00,
    "Receptions":3.00,
    "ReceivingYards":12.00,
    "ReceivingYardsPerReception":4,
    "ReceivingTouchdowns":1.00,
    "ReceivingLong":9.00,
    "Fumbles":0.00,
    "FumblesLost":0.00,
    "PuntReturns":0.00,
    "PuntReturnYards":0.00,
    "PuntReturnYardsPerAttempt":0,
    "PuntReturnTouchdowns":0.00,
    "PuntReturnLong":0.00,
    "KickReturns":0.00,
    "KickReturnYards":0.00,
    "KickReturnYardsPerAttempt":0,
    "KickReturnTouchdowns":0.00,
    "KickReturnLong":0.00,
    "SoloTackles":0.00,
    "AssistedTackles":0.00,
    "TacklesForLoss":0.00,
    "Sacks":0.00,
    "SackYards":0.00,
    "QuarterbackHits":0.00,
    "PassesDefended":0.00,
    "FumblesForced":0.00,
    "FumblesRecovered":0.00,
    "FumbleReturnYards":0.00,
    "FumbleReturnTouchdowns":0.00,
    "Interceptions":0.00,
    "InterceptionReturnYards":0.00,
    "InterceptionReturnTouchdowns":0.00,
    "BlockedKicks":0.00,
    "SpecialTeamsSoloTackles":0.00,
    "SpecialTeamsAssistedTackles":0.00,
    "MiscSoloTackles":0.00,
    "MiscAssistedTackles":0.00,
    "Punts":0.00,
    "PuntYards":0.00,
    "PuntAverage":0,
    "FieldGoalsAttempted":0.00,
    "FieldGoalsMade":0.00,
    "FieldGoalsLongestMade":0.00,
    "ExtraPointsMade":0.00,
    "TwoPointConversionPasses":0.00,
    "TwoPointConversionRuns":0.00,
    "TwoPointConversionReceptions":0.00,
    "FantasyPoints":7.20,
    "FantasyPointsPPR":10.20,
    "ReceptionPercentage":60.0,
    "ReceivingYardsPerTarget":2.4,
    "Tackles":0,
    "OffensiveTouchdowns":1,
    "DefensiveTouchdowns":0,
    "SpecialTeamsTouchdowns":0,
    "Touchdowns":1,
    "FantasyPosition":"WR",
    "FieldGoalPercentage":0,
    "PlayerSeasonID":162025883,
    "FumblesOwnRecoveries":0.00,
    "FumblesOutOfBounds":0.00,
    "KickReturnFairCatches":0.00,
    "PuntReturnFairCatches":0.00,
    "PuntTouchbacks":0.00,
    "PuntInside20":0.00,
    "PuntNetAverage":0,
    "ExtraPointsAttempted":0.00,
    "BlockedKickReturnTouchdowns":0.00,
    "FieldGoalReturnTouchdowns":0.00,
    "Safeties":0.00,
    "FieldGoalsHadBlocked":0.00,
    "PuntsHadBlocked":0.00,
    "ExtraPointsHadBlocked":0.00,
    "PuntLong":0.00,
    "BlockedKickReturnYards":0.00,
    "FieldGoalReturnYards":0.00,
    "PuntNetYards":0.00,
    "SpecialTeamsFumblesForced":0.00,
    "SpecialTeamsFumblesRecovered":0.00,
    "MiscFumblesForced":0.00,
    "MiscFumblesRecovered":0.00,
    "ShortName":"Brittan Golden",
    "SafetiesAllowed":0.00,
    "Temperature":75,
    "Humidity":46,
    "WindSpeed":5,
    "OffensiveSnapsPlayed":null,
    "DefensiveSnapsPlayed":null,
    "SpecialTeamsSnapsPlayed":null,
    "OffensiveTeamSnaps":226,
    "DefensiveTeamSnaps":null,
    "SpecialTeamsTeamSnaps":null,
    "AuctionValue":null,
    "AuctionValuePPR":null,
    "TwoPointConversionReturns":0.00,
    "FantasyPointsFanDuel":8.70,
    "FieldGoalsMade0to19":0.00,
    "FieldGoalsMade20to29":0.00,
    "FieldGoalsMade30to39":0.00,
    "FieldGoalsMade40to49":0.00,
    "FieldGoalsMade50Plus":0.00,
    "FantasyPointsDraftKings":10.20,
    "FantasyPointsYahoo":8.70,
    "AverageDraftPosition":null,
    "AverageDraftPositionPPR":null,
    "TeamID":1,
    "GlobalTeamID":1,
    "FantasyPointsFantasyDraft":10.20
  },
  {
    "PlayerID":5571,
    "SeasonType":1,
    "Season":2016,
    "Team":"ARI",
    "Number":11,
    "Name":"Larry Fitzgerald",
    "Position":"WR",
    "PositionCategory":"OFF",
    "Activated":16,
    "Played":16,
    "Started":16,
    "PassingAttempts":0.00,
    "PassingCompletions":0.00,
    "PassingYards":0.00,
    "PassingCompletionPercentage":0,
    "PassingYardsPerAttempt":0,
    "PassingYardsPerCompletion":0,
    "PassingTouchdowns":0.00,
    "PassingInterceptions":0.00,
    "PassingRating":0,
    "PassingLong":0.00,
    "PassingSacks":0.00,
    "PassingSackYards":0.00,
    "RushingAttempts":0.00,
    "RushingYards":0.00,
    "RushingYardsPerAttempt":0,
    "RushingTouchdowns":0.00,
    "RushingLong":0.00,
    "ReceivingTargets":37.00,
    "Receptions":24.00,
    "ReceivingYards":202.00,
    "ReceivingYardsPerReception":8.4,
    "ReceivingTouchdowns":1.00,
    "ReceivingLong":19.00,
    "Fumbles":1.00,
    "FumblesLost":1.00,
    "PuntReturns":0.00,
    "PuntReturnYards":0.00,
    "PuntReturnYardsPerAttempt":0,
    "PuntReturnTouchdowns":0.00,
    "PuntReturnLong":0.00,
    "KickReturns":0.00,
    "KickReturnYards":0.00,
    "KickReturnYardsPerAttempt":0,
    "KickReturnTouchdowns":0.00,
    "KickReturnLong":0.00,
    "SoloTackles":0.00,
    "AssistedTackles":0.00,
    "TacklesForLoss":0.00,
    "Sacks":0.00,
    "SackYards":0.00,
    "QuarterbackHits":0.00,
    "PassesDefended":0.00,
    "FumblesForced":0.00,
    "FumblesRecovered":0.00,
    "FumbleReturnYards":0.00,
    "FumbleReturnTouchdowns":0.00,
    "Interceptions":0.00,
    "InterceptionReturnYards":0.00,
    "InterceptionReturnTouchdowns":0.00,
    "BlockedKicks":0.00,
    "SpecialTeamsSoloTackles":0.00,
    "SpecialTeamsAssistedTackles":0.00,
    "MiscSoloTackles":0.00,
    "MiscAssistedTackles":0.00,
    "Punts":0.00,
    "PuntYards":0.00,
    "PuntAverage":0,
    "FieldGoalsAttempted":0.00,
    "FieldGoalsMade":0.00,
    "FieldGoalsLongestMade":0.00,
    "ExtraPointsMade":0.00,
    "TwoPointConversionPasses":0.00,
    "TwoPointConversionRuns":0.00,
    "TwoPointConversionReceptions":0.00,
    "FantasyPoints":24.20,
    "FantasyPointsPPR":48.20,
    "ReceptionPercentage":64.9,
    "ReceivingYardsPerTarget":5.5,
    "Tackles":0,
    "OffensiveTouchdowns":1,
    "DefensiveTouchdowns":0,
    "SpecialTeamsTouchdowns":0,
    "Touchdowns":1,
    "FantasyPosition":"WR",
    "FieldGoalPercentage":0,
    "PlayerSeasonID":15524524,
    "FumblesOwnRecoveries":0.00,
    "FumblesOutOfBounds":0.00,
    "KickReturnFairCatches":0.00,
    "PuntReturnFairCatches":0.00,
    "PuntTouchbacks":0.00,
    "PuntInside20":0.00,
    "PuntNetAverage":0,
    "ExtraPointsAttempted":0.00,
    "BlockedKickReturnTouchdowns":0.00,
    "FieldGoalReturnTouchdowns":0.00,
    "Safeties":0.00,
    "FieldGoalsHadBlocked":0.00,
    "PuntsHadBlocked":0.00,
    "ExtraPointsHadBlocked":0.00,
    "PuntLong":0.00,
    "BlockedKickReturnYards":0.00,
    "FieldGoalReturnYards":0.00,
    "PuntNetYards":0.00,
    "SpecialTeamsFumblesForced":0.00,
    "SpecialTeamsFumblesRecovered":0.00,
    "MiscFumblesForced":0.00,
    "MiscFumblesRecovered":0.00,
    "ShortName":"Larry Fitzgerald",
    "SafetiesAllowed":0.00,
    "Temperature":71,
    "Humidity":47,
    "WindSpeed":3,
    "OffensiveSnapsPlayed":null,
    "DefensiveSnapsPlayed":null,
    "SpecialTeamsSnapsPlayed":null,
    "OffensiveTeamSnaps":226,
    "DefensiveTeamSnaps":null,
    "SpecialTeamsTeamSnaps":null,
    "AuctionValue":null,
    "AuctionValuePPR":null,
    "TwoPointConversionReturns":0.00,
    "FantasyPointsFanDuel":36.20,
    "FieldGoalsMade0to19":0.00,
    "FieldGoalsMade20to29":0.00,
    "FieldGoalsMade30to39":0.00,
    "FieldGoalsMade40to49":0.00,
    "FieldGoalsMade50Plus":0.00,
    "FantasyPointsDraftKings":49.20,
    "FantasyPointsYahoo":36.20,
    "AverageDraftPosition":null,
    "AverageDraftPositionPPR":null,
    "TeamID":1,
    "GlobalTeamID":1,
    "FantasyPointsFantasyDraft":49.20
  },
  {
    "PlayerID":16640,
    "SeasonType":1,
    "Season":2016,
    "Team":"ARI",
    "Number":12,
    "Name":"John Brown",
    "Position":"WR",
    "PositionCategory":"OFF",
    "Activated":15,
    "Played":15,
    "Started":6,
    "PassingAttempts":0.00,
    "PassingCompletions":0.00,
    "PassingYards":0.00,
    "PassingCompletionPercentage":0,
    "PassingYardsPerAttempt":0,
    "PassingYardsPerCompletion":0,
    "PassingTouchdowns":0.00,
    "PassingInterceptions":0.00,
    "PassingRating":0,
    "PassingLong":0.00,
    "PassingSacks":0.00,
    "PassingSackYards":0.00,
    "RushingAttempts":0.00,
    "RushingYards":0.00,
    "RushingYardsPerAttempt":0,
    "RushingTouchdowns":0.00,
    "RushingLong":0.00,
    "ReceivingTargets":18.00,
    "Receptions":9.00,
    "ReceivingYards":112.00,
    "ReceivingYardsPerReception":12.4,
    "ReceivingTouchdowns":1.00,
    "ReceivingLong":20.00,
    "Fumbles":0.00,
    "FumblesLost":0.00,
    "PuntReturns":0.00,
    "PuntReturnYards":0.00,
    "PuntReturnYardsPerAttempt":0,
    "PuntReturnTouchdowns":0.00,
    "PuntReturnLong":0.00,
    "KickReturns":0.00,
    "KickReturnYards":0.00,
    "KickReturnYardsPerAttempt":0,
    "KickReturnTouchdowns":0.00,
    "KickReturnLong":0.00,
    "SoloTackles":0.00,
    "AssistedTackles":0.00,
    "TacklesForLoss":0.00,
    "Sacks":0.00,
    "SackYards":0.00,
    "QuarterbackHits":0.00,
    "PassesDefended":0.00,
    "FumblesForced":0.00,
    "FumblesRecovered":0.00,
    "FumbleReturnYards":0.00,
    "FumbleReturnTouchdowns":0.00,
    "Interceptions":0.00,
    "InterceptionReturnYards":0.00,
    "InterceptionReturnTouchdowns":0.00,
    "BlockedKicks":0.00,
    "SpecialTeamsSoloTackles":0.00,
    "SpecialTeamsAssistedTackles":0.00,
    "MiscSoloTackles":0.00,
    "MiscAssistedTackles":0.00,
    "Punts":0.00,
    "PuntYards":0.00,
    "PuntAverage":0,
    "FieldGoalsAttempted":0.00,
    "FieldGoalsMade":0.00,
    "FieldGoalsLongestMade":0.00,
    "ExtraPointsMade":0.00,
    "TwoPointConversionPasses":0.00,
    "TwoPointConversionRuns":0.00,
    "TwoPointConversionReceptions":0.00,
    "FantasyPoints":17.20,
    "FantasyPointsPPR":26.20,
    "ReceptionPercentage":50.0,
    "ReceivingYardsPerTarget":6.2,
    "Tackles":0,
    "OffensiveTouchdowns":1,
    "DefensiveTouchdowns":0,
    "SpecialTeamsTouchdowns":0,
    "Touchdowns":1,
    "FantasyPosition":"WR",
    "FieldGoalPercentage":0,
    "PlayerSeasonID":15524908,
    "FumblesOwnRecoveries":0.00,
    "FumblesOutOfBounds":0.00,
    "KickReturnFairCatches":0.00,
    "PuntReturnFairCatches":0.00,
    "PuntTouchbacks":0.00,
    "PuntInside20":0.00,
    "PuntNetAverage":0,
    "ExtraPointsAttempted":0.00,
    "BlockedKickReturnTouchdowns":0.00,
    "FieldGoalReturnTouchdowns":0.00,
    "Safeties":0.00,
    "FieldGoalsHadBlocked":0.00,
    "PuntsHadBlocked":0.00,
    "ExtraPointsHadBlocked":0.00,
    "PuntLong":0.00,
    "BlockedKickReturnYards":0.00,
    "FieldGoalReturnYards":0.00,
    "PuntNetYards":0.00,
    "SpecialTeamsFumblesForced":0.00,
    "SpecialTeamsFumblesRecovered":0.00,
    "MiscFumblesForced":0.00,
    "MiscFumblesRecovered":0.00,
    "ShortName":"John Brown",
    "SafetiesAllowed":0.00,
    "Temperature":71,
    "Humidity":47,
    "WindSpeed":3,
    "OffensiveSnapsPlayed":null,
    "DefensiveSnapsPlayed":null,
    "SpecialTeamsSnapsPlayed":null,
    "OffensiveTeamSnaps":226,
    "DefensiveTeamSnaps":null,
    "SpecialTeamsTeamSnaps":null,
    "AuctionValue":null,
    "AuctionValuePPR":null,
    "TwoPointConversionReturns":0.00,
    "FantasyPointsFanDuel":21.70,
    "FieldGoalsMade0to19":0.00,
    "FieldGoalsMade20to29":0.00,
    "FieldGoalsMade30to39":0.00,
    "FieldGoalsMade40to49":0.00,
    "FieldGoalsMade50Plus":0.00,
    "FantasyPointsDraftKings":26.20,
    "FantasyPointsYahoo":21.70,
    "AverageDraftPosition":null,
    "AverageDraftPositionPPR":null,
    "TeamID":1,
    "GlobalTeamID":1,
    "FantasyPointsFantasyDraft":26.20
  },
  {
    "PlayerID":15509,
    "SeasonType":1,
    "Season":2016,
    "Team":"ARI",
    "Number":13,
    "Name":"Jaron Brown",
    "Position":"WR",
    "PositionCategory":"OFF",
    "Activated":7,
    "Played":7,
    "Started":2,
    "PassingAttempts":0.00,
    "PassingCompletions":0.00,
    "PassingYards":0.00,
    "PassingCompletionPercentage":0,
    "PassingYardsPerAttempt":0,
    "PassingYardsPerCompletion":0,
    "PassingTouchdowns":0.00,
    "PassingInterceptions":0.00,
    "PassingRating":0,
    "PassingLong":0.00,
    "PassingSacks":0.00,
    "PassingSackYards":0.00,
    "RushingAttempts":0.00,
    "RushingYards":0.00,
    "RushingYardsPerAttempt":0,
    "RushingTouchdowns":0.00,
    "RushingLong":0.00,
    "ReceivingTargets":8.00,
    "Receptions":3.00,
    "ReceivingYards":68.00,
    "ReceivingYardsPerReception":22.7,
    "ReceivingTouchdowns":0.00,
    "ReceivingLong":27.00,
    "Fumbles":0.00,
    "FumblesLost":0.00,
    "PuntReturns":0.00,
    "PuntReturnYards":0.00,
    "PuntReturnYardsPerAttempt":0,
    "PuntReturnTouchdowns":0.00,
    "PuntReturnLong":0.00,
    "KickReturns":0.00,
    "KickReturnYards":0.00,
    "KickReturnYardsPerAttempt":0,
    "KickReturnTouchdowns":0.00,
    "KickReturnLong":0.00,
    "SoloTackles":0.00,
    "AssistedTackles":0.00,
    "TacklesForLoss":0.00,
    "Sacks":0.00,
    "SackYards":0.00,
    "QuarterbackHits":0.00,
    "PassesDefended":0.00,
    "FumblesForced":0.00,
    "FumblesRecovered":0.00,
    "FumbleReturnYards":0.00,
    "FumbleReturnTouchdowns":0.00,
    "Interceptions":0.00,
    "InterceptionReturnYards":0.00,
    "InterceptionReturnTouchdowns":0.00,
    "BlockedKicks":0.00,
    "SpecialTeamsSoloTackles":0.00,
    "SpecialTeamsAssistedTackles":0.00,
    "MiscSoloTackles":0.00,
    "MiscAssistedTackles":0.00,
    "Punts":0.00,
    "PuntYards":0.00,
    "PuntAverage":0,
    "FieldGoalsAttempted":0.00,
    "FieldGoalsMade":0.00,
    "FieldGoalsLongestMade":0.00,
    "ExtraPointsMade":0.00,
    "TwoPointConversionPasses":0.00,
    "TwoPointConversionRuns":0.00,
    "TwoPointConversionReceptions":0.00,
    "FantasyPoints":6.80,
    "FantasyPointsPPR":9.80,
    "ReceptionPercentage":37.5,
    "ReceivingYardsPerTarget":8.5,
    "Tackles":0,
    "OffensiveTouchdowns":0,
    "DefensiveTouchdowns":0,
    "SpecialTeamsTouchdowns":0,
    "Touchdowns":0,
    "FantasyPosition":"WR",
    "FieldGoalPercentage":0,
    "PlayerSeasonID":15524713,
    "FumblesOwnRecoveries":0.00,
    "FumblesOutOfBounds":0.00,
    "KickReturnFairCatches":0.00,
    "PuntReturnFairCatches":0.00,
    "PuntTouchbacks":0.00,
    "PuntInside20":0.00,
    "PuntNetAverage":0,
    "ExtraPointsAttempted":0.00,
    "BlockedKickReturnTouchdowns":0.00,
    "FieldGoalReturnTouchdowns":0.00,
    "Safeties":0.00,
    "FieldGoalsHadBlocked":0.00,
    "PuntsHadBlocked":0.00,
    "ExtraPointsHadBlocked":0.00,
    "PuntLong":0.00,
    "BlockedKickReturnYards":0.00,
    "FieldGoalReturnYards":0.00,
    "PuntNetYards":0.00,
    "SpecialTeamsFumblesForced":0.00,
    "SpecialTeamsFumblesRecovered":0.00,
    "MiscFumblesForced":0.00,
    "MiscFumblesRecovered":0.00,
    "ShortName":"Jaron Brown",
    "SafetiesAllowed":0.00,
    "Temperature":71,
    "Humidity":47,
    "WindSpeed":3,
    "OffensiveSnapsPlayed":null,
    "DefensiveSnapsPlayed":null,
    "SpecialTeamsSnapsPlayed":null,
    "OffensiveTeamSnaps":226,
    "DefensiveTeamSnaps":null,
    "SpecialTeamsTeamSnaps":null,
    "AuctionValue":null,
    "AuctionValuePPR":null,
    "TwoPointConversionReturns":0.00,
    "FantasyPointsFanDuel":8.30,
    "FieldGoalsMade0to19":0.00,
    "FieldGoalsMade20to29":0.00,
    "FieldGoalsMade30to39":0.00,
    "FieldGoalsMade40to49":0.00,
    "FieldGoalsMade50Plus":0.00,
    "FantasyPointsDraftKings":9.80,
    "FantasyPointsYahoo":8.30,
    "AverageDraftPosition":null,
    "AverageDraftPositionPPR":null,
    "TeamID":1,
    "GlobalTeamID":1,
    "FantasyPointsFantasyDraft":9.80
  },
  {
    "PlayerID":16919,
    "SeasonType":1,
    "Season":2016,
    "Team":"ARI",
    "Number":14,
    "Name":"JJ Nelson",
    "Position":"WR",
    "PositionCategory":"OFF",
    "Activated":15,
    "Played":15,
    "Started":6,
    "PassingAttempts":0.00,
    "PassingCompletions":0.00,
    "PassingYards":0.00,
    "PassingCompletionPercentage":0,
    "PassingYardsPerAttempt":0,
    "PassingYardsPerCompletion":0,
    "PassingTouchdowns":0.00,
    "PassingInterceptions":0.00,
    "PassingRating":0,
    "PassingLong":0.00,
    "PassingSacks":0.00,
    "PassingSackYards":0.00,
    "RushingAttempts":0.00,
    "RushingYards":0.00,
    "RushingYardsPerAttempt":0,
    "RushingTouchdowns":0.00,
    "RushingLong":0.00,
    "ReceivingTargets":20.00,
    "Receptions":9.00,
    "ReceivingYards":143.00,
    "ReceivingYardsPerReception":15.9,
    "ReceivingTouchdowns":2.00,
    "ReceivingLong":40.00,
    "Fumbles":1.00,
    "FumblesLost":1.00,
    "PuntReturns":0.00,
    "PuntReturnYards":0.00,
    "PuntReturnYardsPerAttempt":0,
    "PuntReturnTouchdowns":0.00,
    "PuntReturnLong":0.00,
    "KickReturns":0.00,
    "KickReturnYards":0.00,
    "KickReturnYardsPerAttempt":0,
    "KickReturnTouchdowns":0.00,
    "KickReturnLong":0.00,
    "SoloTackles":0.00,
    "AssistedTackles":0.00,
    "TacklesForLoss":0.00,
    "Sacks":0.00,
    "SackYards":0.00,
    "QuarterbackHits":0.00,
    "PassesDefended":0.00,
    "FumblesForced":0.00,
    "FumblesRecovered":0.00,
    "FumbleReturnYards":0.00,
    "FumbleReturnTouchdowns":0.00,
    "Interceptions":0.00,
    "InterceptionReturnYards":0.00,
    "InterceptionReturnTouchdowns":0.00,
    "BlockedKicks":0.00,
    "SpecialTeamsSoloTackles":0.00,
    "SpecialTeamsAssistedTackles":0.00,
    "MiscSoloTackles":0.00,
    "MiscAssistedTackles":0.00,
    "Punts":0.00,
    "PuntYards":0.00,
    "PuntAverage":0,
    "FieldGoalsAttempted":0.00,
    "FieldGoalsMade":0.00,
    "FieldGoalsLongestMade":0.00,
    "ExtraPointsMade":0.00,
    "TwoPointConversionPasses":0.00,
    "TwoPointConversionRuns":0.00,
    "TwoPointConversionReceptions":0.00,
    "FantasyPoints":24.30,
    "FantasyPointsPPR":33.30,
    "ReceptionPercentage":45.0,
    "ReceivingYardsPerTarget":7.2,
    "Tackles":0,
    "OffensiveTouchdowns":2,
    "DefensiveTouchdowns":0,
    "SpecialTeamsTouchdowns":0,
    "Touchdowns":2,
    "FantasyPosition":"WR",
    "FieldGoalPercentage":0,
    "PlayerSeasonID":15524798,
    "FumblesOwnRecoveries":0.00,
    "FumblesOutOfBounds":0.00,
    "KickReturnFairCatches":0.00,
    "PuntReturnFairCatches":0.00,
    "PuntTouchbacks":0.00,
    "PuntInside20":0.00,
    "PuntNetAverage":0,
    "ExtraPointsAttempted":0.00,
    "BlockedKickReturnTouchdowns":0.00,
    "FieldGoalReturnTouchdowns":0.00,
    "Safeties":0.00,
    "FieldGoalsHadBlocked":0.00,
    "PuntsHadBlocked":0.00,
    "ExtraPointsHadBlocked":0.00,
    "PuntLong":0.00,
    "BlockedKickReturnYards":0.00,
    "FieldGoalReturnYards":0.00,
    "PuntNetYards":0.00,
    "SpecialTeamsFumblesForced":0.00,
    "SpecialTeamsFumblesRecovered":0.00,
    "MiscFumblesForced":0.00,
    "MiscFumblesRecovered":0.00,
    "ShortName":"JJ Nelson",
    "SafetiesAllowed":0.00,
    "Temperature":71,
    "Humidity":47,
    "WindSpeed":3,
    "OffensiveSnapsPlayed":null,
    "DefensiveSnapsPlayed":null,
    "SpecialTeamsSnapsPlayed":null,
    "OffensiveTeamSnaps":226,
    "DefensiveTeamSnaps":null,
    "SpecialTeamsTeamSnaps":null,
    "AuctionValue":null,
    "AuctionValuePPR":null,
    "TwoPointConversionReturns":0.00,
    "FantasyPointsFanDuel":28.80,
    "FieldGoalsMade0to19":0.00,
    "FieldGoalsMade20to29":0.00,
    "FieldGoalsMade30to39":0.00,
    "FieldGoalsMade40to49":0.00,
    "FieldGoalsMade50Plus":0.00,
    "FantasyPointsDraftKings":34.30,
    "FantasyPointsYahoo":28.80,
    "AverageDraftPosition":null,
    "AverageDraftPositionPPR":null,
    "TeamID":1,
    "GlobalTeamID":1,
    "FantasyPointsFantasyDraft":34.30
  },
  {
    "PlayerID":18711,
    "SeasonType":1,
    "Season":2016,
    "Team":"ARI",
    "Number":18,
    "Name":"Marquis Bundy",
    "Position":"WR",
    "PositionCategory":"OFF",
    "Activated":1,
    "Played":0,
    "Started":0,
    "PassingAttempts":0.00,
    "PassingCompletions":0.00,
    "PassingYards":0.00,
    "PassingCompletionPercentage":0,
    "PassingYardsPerAttempt":0,
    "PassingYardsPerCompletion":0,
    "PassingTouchdowns":0.00,
    "PassingInterceptions":0.00,
    "PassingRating":0,
    "PassingLong":null,
    "PassingSacks":0.00,
    "PassingSackYards":0.00,
    "RushingAttempts":0.00,
    "RushingYards":0.00,
    "RushingYardsPerAttempt":0,
    "RushingTouchdowns":0.00,
    "RushingLong":null,
    "ReceivingTargets":0.00,
    "Receptions":0.00,
    "ReceivingYards":0.00,
    "ReceivingYardsPerReception":0,
    "ReceivingTouchdowns":0.00,
    "ReceivingLong":null,
    "Fumbles":0.00,
    "FumblesLost":0.00,
    "PuntReturns":0.00,
    "PuntReturnYards":0.00,
    "PuntReturnYardsPerAttempt":0,
    "PuntReturnTouchdowns":0.00,
    "PuntReturnLong":null,
    "KickReturns":0.00,
    "KickReturnYards":0.00,
    "KickReturnYardsPerAttempt":0,
    "KickReturnTouchdowns":0.00,
    "KickReturnLong":null,
    "SoloTackles":0.00,
    "AssistedTackles":0.00,
    "TacklesForLoss":0.00,
    "Sacks":0.00,
    "SackYards":0.00,
    "QuarterbackHits":0.00,
    "PassesDefended":0.00,
    "FumblesForced":0.00,
    "FumblesRecovered":0.00,
    "FumbleReturnYards":0.00,
    "FumbleReturnTouchdowns":0.00,
    "Interceptions":0.00,
    "InterceptionReturnYards":0.00,
    "InterceptionReturnTouchdowns":0.00,
    "BlockedKicks":0.00,
    "SpecialTeamsSoloTackles":0.00,
    "SpecialTeamsAssistedTackles":0.00,
    "MiscSoloTackles":0.00,
    "MiscAssistedTackles":0.00,
    "Punts":0.00,
    "PuntYards":0.00,
    "PuntAverage":0,
    "FieldGoalsAttempted":0.00,
    "FieldGoalsMade":0.00,
    "FieldGoalsLongestMade":null,
    "ExtraPointsMade":0.00,
    "TwoPointConversionPasses":0.00,
    "TwoPointConversionRuns":0.00,
    "TwoPointConversionReceptions":0.00,
    "FantasyPoints":0.00,
    "FantasyPointsPPR":0.00,
    "ReceptionPercentage":0,
    "ReceivingYardsPerTarget":0,
    "Tackles":0,
    "OffensiveTouchdowns":0,
    "DefensiveTouchdowns":0,
    "SpecialTeamsTouchdowns":0,
    "Touchdowns":0,
    "FantasyPosition":"WR",
    "FieldGoalPercentage":0,
    "PlayerSeasonID":162050003,
    "FumblesOwnRecoveries":0.00,
    "FumblesOutOfBounds":0.00,
    "KickReturnFairCatches":0.00,
    "PuntReturnFairCatches":0.00,
    "PuntTouchbacks":0.00,
    "PuntInside20":0.00,
    "PuntNetAverage":0,
    "ExtraPointsAttempted":0.00,
    "BlockedKickReturnTouchdowns":0.00,
    "FieldGoalReturnTouchdowns":0.00,
    "Safeties":0.00,
    "FieldGoalsHadBlocked":0.00,
    "PuntsHadBlocked":0.00,
    "ExtraPointsHadBlocked":0.00,
    "PuntLong":null,
    "BlockedKickReturnYards":0.00,
    "FieldGoalReturnYards":0.00,
    "PuntNetYards":0.00,
    "SpecialTeamsFumblesForced":0.00,
    "SpecialTeamsFumblesRecovered":0.00,
    "MiscFumblesForced":0.00,
    "MiscFumblesRecovered":0.00,
    "ShortName":"Marquis Bundy",
    "SafetiesAllowed":0.00,
    "Temperature":null,
    "Humidity":null,
    "WindSpeed":null,
    "OffensiveSnapsPlayed":null,
    "DefensiveSnapsPlayed":null,
    "SpecialTeamsSnapsPlayed":null,
    "OffensiveTeamSnaps":226,
    "DefensiveTeamSnaps":null,
    "SpecialTeamsTeamSnaps":null,
    "AuctionValue":null,
    "AuctionValuePPR":null,
    "TwoPointConversionReturns":0.00,
    "FantasyPointsFanDuel":0.00,
    "FieldGoalsMade0to19":0.00,
    "FieldGoalsMade20to29":0.00,
    "FieldGoalsMade30to39":0.00,
    "FieldGoalsMade40to49":0.00,
    "FieldGoalsMade50Plus":0.00,
    "FantasyPointsDraftKings":0.00,
    "FantasyPointsYahoo":0.00,
    "AverageDraftPosition":null,
    "AverageDraftPositionPPR":null,
    "TeamID":1,
    "GlobalTeamID":1,
    "FantasyPointsFantasyDraft":0.00
  },
  {
    "PlayerID":18616,
    "SeasonType":1,
    "Season":2016,
    "Team":"ARI",
    "Number":19,
    "Name":"Chris Hubert",
    "Position":"WR",
    "PositionCategory":"OFF",
    "Activated":0,
    "Played":0,
    "Started":0,
    "PassingAttempts":0.00,
    "PassingCompletions":0.00,
    "PassingYards":0.00,
    "PassingCompletionPercentage":0,
    "PassingYardsPerAttempt":0,
    "PassingYardsPerCompletion":0,
    "PassingTouchdowns":0.00,
    "PassingInterceptions":0.00,
    "PassingRating":0,
    "PassingLong":null,
    "PassingSacks":0.00,
    "PassingSackYards":0.00,
    "RushingAttempts":0.00,
    "RushingYards":0.00,
    "RushingYardsPerAttempt":0,
    "RushingTouchdowns":0.00,
    "RushingLong":null,
    "ReceivingTargets":0.00,
    "Receptions":0.00,
    "ReceivingYards":0.00,
    "ReceivingYardsPerReception":0,
    "ReceivingTouchdowns":0.00,
    "ReceivingLong":null,
    "Fumbles":0.00,
    "FumblesLost":0.00,
    "PuntReturns":0.00,
    "PuntReturnYards":0.00,
    "PuntReturnYardsPerAttempt":0,
    "PuntReturnTouchdowns":0.00,
    "PuntReturnLong":null,
    "KickReturns":0.00,
    "KickReturnYards":0.00,
    "KickReturnYardsPerAttempt":0,
    "KickReturnTouchdowns":0.00,
    "KickReturnLong":null,
    "SoloTackles":0.00,
    "AssistedTackles":0.00,
    "TacklesForLoss":0.00,
    "Sacks":0.00,
    "SackYards":0.00,
    "QuarterbackHits":0.00,
    "PassesDefended":0.00,
    "FumblesForced":0.00,
    "FumblesRecovered":0.00,
    "FumbleReturnYards":0.00,
    "FumbleReturnTouchdowns":0.00,
    "Interceptions":0.00,
    "InterceptionReturnYards":0.00,
    "InterceptionReturnTouchdowns":0.00,
    "BlockedKicks":0.00,
    "SpecialTeamsSoloTackles":0.00,
    "SpecialTeamsAssistedTackles":0.00,
    "MiscSoloTackles":0.00,
    "MiscAssistedTackles":0.00,
    "Punts":0.00,
    "PuntYards":0.00,
    "PuntAverage":0,
    "FieldGoalsAttempted":0.00,
    "FieldGoalsMade":0.00,
    "FieldGoalsLongestMade":null,
    "ExtraPointsMade":0.00,
    "TwoPointConversionPasses":0.00,
    "TwoPointConversionRuns":0.00,
    "TwoPointConversionReceptions":0.00,
    "FantasyPoints":0.00,
    "FantasyPointsPPR":0.00,
    "ReceptionPercentage":0,
    "ReceivingYardsPerTarget":0,
    "Tackles":0,
    "OffensiveTouchdowns":0,
    "DefensiveTouchdowns":0,
    "SpecialTeamsTouchdowns":0,
    "Touchdowns":0,
    "FantasyPosition":"WR",
    "FieldGoalPercentage":0,
    "PlayerSeasonID":162038434,
    "FumblesOwnRecoveries":0.00,
    "FumblesOutOfBounds":0.00,
    "KickReturnFairCatches":0.00,
    "PuntReturnFairCatches":0.00,
    "PuntTouchbacks":0.00,
    "PuntInside20":0.00,
    "PuntNetAverage":0,
    "ExtraPointsAttempted":0.00,
    "BlockedKickReturnTouchdowns":0.00,
    "FieldGoalReturnTouchdowns":0.00,
    "Safeties":0.00,
    "FieldGoalsHadBlocked":0.00,
    "PuntsHadBlocked":0.00,
    "ExtraPointsHadBlocked":0.00,
    "PuntLong":null,
    "BlockedKickReturnYards":0.00,
    "FieldGoalReturnYards":0.00,
    "PuntNetYards":0.00,
    "SpecialTeamsFumblesForced":0.00,
    "SpecialTeamsFumblesRecovered":0.00,
    "MiscFumblesForced":0.00,
    "MiscFumblesRecovered":0.00,
    "ShortName":"Chris Hubert",
    "SafetiesAllowed":0.00,
    "Temperature":85,
    "Humidity":53,
    "WindSpeed":5,
    "OffensiveSnapsPlayed":null,
    "DefensiveSnapsPlayed":null,
    "SpecialTeamsSnapsPlayed":null,
    "OffensiveTeamSnaps":226,
    "DefensiveTeamSnaps":null,
    "SpecialTeamsTeamSnaps":null,
    "AuctionValue":null,
    "AuctionValuePPR":null,
    "TwoPointConversionReturns":0.00,
    "FantasyPointsFanDuel":0.00,
    "FieldGoalsMade0to19":0.00,
    "FieldGoalsMade20to29":0.00,
    "FieldGoalsMade30to39":0.00,
    "FieldGoalsMade40to49":0.00,
    "FieldGoalsMade50Plus":0.00,
    "FantasyPointsDraftKings":0.00,
    "FantasyPointsYahoo":0.00,
    "AverageDraftPosition":null,
    "AverageDraftPositionPPR":null,
    "TeamID":1,
    "GlobalTeamID":1,
    "FantasyPointsFantasyDraft":0.00
  },
  {
    "PlayerID":6828,
    "SeasonType":1,
    "Season":2016,
    "Team":"ARI",
    "Number":23,
    "Name":"Chris Johnson",
    "Position":"RB",
    "PositionCategory":"OFF",
    "Activated":4,
    "Played":4,
    "Started":0,
    "PassingAttempts":0.00,
    "PassingCompletions":0.00,
    "PassingYards":0.00,
    "PassingCompletionPercentage":0,
    "PassingYardsPerAttempt":0,
    "PassingYardsPerCompletion":0,
    "PassingTouchdowns":0.00,
    "PassingInterceptions":0.00,
    "PassingRating":0,
    "PassingLong":0.00,
    "PassingSacks":0.00,
    "PassingSackYards":0.00,
    "RushingAttempts":2.00,
    "RushingYards":5.00,
    "RushingYardsPerAttempt":2.5,
    "RushingTouchdowns":0.00,
    "RushingLong":3.00,
    "ReceivingTargets":1.00,
    "Receptions":0.00,
    "ReceivingYards":0.00,
    "ReceivingYardsPerReception":0,
    "ReceivingTouchdowns":0.00,
    "ReceivingLong":0.00,
    "Fumbles":0.00,
    "FumblesLost":0.00,
    "PuntReturns":0.00,
    "PuntReturnYards":0.00,
    "PuntReturnYardsPerAttempt":0,
    "PuntReturnTouchdowns":0.00,
    "PuntReturnLong":0.00,
    "KickReturns":0.00,
    "KickReturnYards":0.00,
    "KickReturnYardsPerAttempt":0,
    "KickReturnTouchdowns":0.00,
    "KickReturnLong":0.00,
    "SoloTackles":0.00,
    "AssistedTackles":0.00,
    "TacklesForLoss":0.00,
    "Sacks":0.00,
    "SackYards":0.00,
    "QuarterbackHits":0.00,
    "PassesDefended":0.00,
    "FumblesForced":0.00,
    "FumblesRecovered":0.00,
    "FumbleReturnYards":0.00,
    "FumbleReturnTouchdowns":0.00,
    "Interceptions":0.00,
    "InterceptionReturnYards":0.00,
    "InterceptionReturnTouchdowns":0.00,
    "BlockedKicks":0.00,
    "SpecialTeamsSoloTackles":0.00,
    "SpecialTeamsAssistedTackles":0.00,
    "MiscSoloTackles":0.00,
    "MiscAssistedTackles":0.00,
    "Punts":0.00,
    "PuntYards":0.00,
    "PuntAverage":0,
    "FieldGoalsAttempted":0.00,
    "FieldGoalsMade":0.00,
    "FieldGoalsLongestMade":0.00,
    "ExtraPointsMade":0.00,
    "TwoPointConversionPasses":0.00,
    "TwoPointConversionRuns":0.00,
    "TwoPointConversionReceptions":0.00,
    "FantasyPoints":0.50,
    "FantasyPointsPPR":0.50,
    "ReceptionPercentage":0,
    "ReceivingYardsPerTarget":0,
    "Tackles":0,
    "OffensiveTouchdowns":0,
    "DefensiveTouchdowns":0,
    "SpecialTeamsTouchdowns":0,
    "Touchdowns":0,
    "FantasyPosition":"RB",
    "FieldGoalPercentage":0,
    "PlayerSeasonID":15524484,
    "FumblesOwnRecoveries":0.00,
    "FumblesOutOfBounds":0.00,
    "KickReturnFairCatches":0.00,
    "PuntReturnFairCatches":0.00,
    "PuntTouchbacks":0.00,
    "PuntInside20":0.00,
    "PuntNetAverage":0,
    "ExtraPointsAttempted":0.00,
    "BlockedKickReturnTouchdowns":0.00,
    "FieldGoalReturnTouchdowns":0.00,
    "Safeties":0.00,
    "FieldGoalsHadBlocked":0.00,
    "PuntsHadBlocked":0.00,
    "ExtraPointsHadBlocked":0.00,
    "PuntLong":0.00,
    "BlockedKickReturnYards":0.00,
    "FieldGoalReturnYards":0.00,
    "PuntNetYards":0.00,
    "SpecialTeamsFumblesForced":0.00,
    "SpecialTeamsFumblesRecovered":0.00,
    "MiscFumblesForced":0.00,
    "MiscFumblesRecovered":0.00,
    "ShortName":"Chris Johnson",
    "SafetiesAllowed":0.00,
    "Temperature":71,
    "Humidity":47,
    "WindSpeed":3,
    "OffensiveSnapsPlayed":null,
    "DefensiveSnapsPlayed":null,
    "SpecialTeamsSnapsPlayed":null,
    "OffensiveTeamSnaps":226,
    "DefensiveTeamSnaps":null,
    "SpecialTeamsTeamSnaps":null,
    "AuctionValue":null,
    "AuctionValuePPR":null,
    "TwoPointConversionReturns":0.00,
    "FantasyPointsFanDuel":0.50,
    "FieldGoalsMade0to19":0.00,
    "FieldGoalsMade20to29":0.00,
    "FieldGoalsMade30to39":0.00,
    "FieldGoalsMade40to49":0.00,
    "FieldGoalsMade50Plus":0.00,
    "FantasyPointsDraftKings":0.50,
    "FantasyPointsYahoo":0.50,
    "AverageDraftPosition":null,
    "AverageDraftPositionPPR":null,
    "TeamID":1,
    "GlobalTeamID":1,
    "FantasyPointsFantasyDraft":0.50
  },
  {
    "PlayerID":15230,
    "SeasonType":1,
    "Season":2016,
    "Team":"ARI",
    "Number":30,
    "Name":"Stepfan Taylor",
    "Position":"RB",
    "PositionCategory":"OFF",
    "Activated":15,
    "Played":15,
    "Started":0,
    "PassingAttempts":0.00,
    "PassingCompletions":0.00,
    "PassingYards":0.00,
    "PassingCompletionPercentage":0,
    "PassingYardsPerAttempt":0,
    "PassingYardsPerCompletion":0,
    "PassingTouchdowns":0.00,
    "PassingInterceptions":0.00,
    "PassingRating":0,
    "PassingLong":0.00,
    "PassingSacks":0.00,
    "PassingSackYards":0.00,
    "RushingAttempts":1.00,
    "RushingYards":12.00,
    "RushingYardsPerAttempt":12,
    "RushingTouchdowns":0.00,
    "RushingLong":12.00,
    "ReceivingTargets":0.00,
    "Receptions":0.00,
    "ReceivingYards":0.00,
    "ReceivingYardsPerReception":0,
    "ReceivingTouchdowns":0.00,
    "ReceivingLong":0.00,
    "Fumbles":0.00,
    "FumblesLost":0.00,
    "PuntReturns":0.00,
    "PuntReturnYards":0.00,
    "PuntReturnYardsPerAttempt":0,
    "PuntReturnTouchdowns":0.00,
    "PuntReturnLong":0.00,
    "KickReturns":0.00,
    "KickReturnYards":0.00,
    "KickReturnYardsPerAttempt":0,
    "KickReturnTouchdowns":0.00,
    "KickReturnLong":0.00,
    "SoloTackles":0.00,
    "AssistedTackles":0.00,
    "TacklesForLoss":0.00,
    "Sacks":0.00,
    "SackYards":0.00,
    "QuarterbackHits":0.00,
    "PassesDefended":0.00,
    "FumblesForced":0.00,
    "FumblesRecovered":0.00,
    "FumbleReturnYards":0.00,
    "FumbleReturnTouchdowns":0.00,
    "Interceptions":0.00,
    "InterceptionReturnYards":0.00,
    "InterceptionReturnTouchdowns":0.00,
    "BlockedKicks":0.00,
    "SpecialTeamsSoloTackles":0.00,
    "SpecialTeamsAssistedTackles":0.00,
    "MiscSoloTackles":0.00,
    "MiscAssistedTackles":0.00,
    "Punts":0.00,
    "PuntYards":0.00,
    "PuntAverage":0,
    "FieldGoalsAttempted":0.00,
    "FieldGoalsMade":0.00,
    "FieldGoalsLongestMade":0.00,
    "ExtraPointsMade":0.00,
    "TwoPointConversionPasses":0.00,
    "TwoPointConversionRuns":0.00,
    "TwoPointConversionReceptions":0.00,
    "FantasyPoints":1.20,
    "FantasyPointsPPR":1.20,
    "ReceptionPercentage":0,
    "ReceivingYardsPerTarget":0,
    "Tackles":0,
    "OffensiveTouchdowns":0,
    "DefensiveTouchdowns":0,
    "SpecialTeamsTouchdowns":0,
    "Touchdowns":0,
    "FantasyPosition":"RB",
    "FieldGoalPercentage":0,
    "PlayerSeasonID":15524666,
    "FumblesOwnRecoveries":0.00,
    "FumblesOutOfBounds":0.00,
    "KickReturnFairCatches":0.00,
    "PuntReturnFairCatches":0.00,
    "PuntTouchbacks":0.00,
    "PuntInside20":0.00,
    "PuntNetAverage":0,
    "ExtraPointsAttempted":0.00,
    "BlockedKickReturnTouchdowns":0.00,
    "FieldGoalReturnTouchdowns":0.00,
    "Safeties":0.00,
    "FieldGoalsHadBlocked":0.00,
    "PuntsHadBlocked":0.00,
    "ExtraPointsHadBlocked":0.00,
    "PuntLong":0.00,
    "BlockedKickReturnYards":0.00,
    "FieldGoalReturnYards":0.00,
    "PuntNetYards":0.00,
    "SpecialTeamsFumblesForced":0.00,
    "SpecialTeamsFumblesRecovered":0.00,
    "MiscFumblesForced":0.00,
    "MiscFumblesRecovered":0.00,
    "ShortName":"Stepfan Taylor",
    "SafetiesAllowed":0.00,
    "Temperature":71,
    "Humidity":47,
    "WindSpeed":3,
    "OffensiveSnapsPlayed":null,
    "DefensiveSnapsPlayed":null,
    "SpecialTeamsSnapsPlayed":null,
    "OffensiveTeamSnaps":226,
    "DefensiveTeamSnaps":null,
    "SpecialTeamsTeamSnaps":null,
    "AuctionValue":null,
    "AuctionValuePPR":null,
    "TwoPointConversionReturns":0.00,
    "FantasyPointsFanDuel":1.20,
    "FieldGoalsMade0to19":0.00,
    "FieldGoalsMade20to29":0.00,
    "FieldGoalsMade30to39":0.00,
    "FieldGoalsMade40to49":0.00,
    "FieldGoalsMade50Plus":0.00,
    "FantasyPointsDraftKings":1.20,
    "FantasyPointsYahoo":1.20,
    "AverageDraftPosition":null,
    "AverageDraftPositionPPR":null,
    "TeamID":1,
    "GlobalTeamID":1,
    "FantasyPointsFantasyDraft":1.20
  },
  {
    "PlayerID":16847,
    "SeasonType":1,
    "Season":2016,
    "Team":"ARI",
    "Number":31,
    "Name":"David Johnson",
    "Position":"RB",
    "PositionCategory":"OFF",
    "Activated":16,
    "Played":16,
    "Started":16,
    "PassingAttempts":0.00,
    "PassingCompletions":0.00,
    "PassingYards":0.00,
    "PassingCompletionPercentage":0,
    "PassingYardsPerAttempt":0,
    "PassingYardsPerCompletion":0,
    "PassingTouchdowns":0.00,
    "PassingInterceptions":0.00,
    "PassingRating":0,
    "PassingLong":0.00,
    "PassingSacks":0.00,
    "PassingSackYards":0.00,
    "RushingAttempts":23.00,
    "RushingYards":85.00,
    "RushingYardsPerAttempt":3.7,
    "RushingTouchdowns":1.00,
    "RushingLong":19.00,
    "ReceivingTargets":37.00,
    "Receptions":26.00,
    "ReceivingYards":256.00,
    "ReceivingYardsPerReception":9.8,
    "ReceivingTouchdowns":2.00,
    "ReceivingLong":24.00,
    "Fumbles":1.00,
    "FumblesLost":1.00,
    "PuntReturns":0.00,
    "PuntReturnYards":0.00,
    "PuntReturnYardsPerAttempt":0,
    "PuntReturnTouchdowns":0.00,
    "PuntReturnLong":0.00,
    "KickReturns":0.00,
    "KickReturnYards":0.00,
    "KickReturnYardsPerAttempt":0,
    "KickReturnTouchdowns":0.00,
    "KickReturnLong":0.00,
    "SoloTackles":0.00,
    "AssistedTackles":0.00,
    "TacklesForLoss":0.00,
    "Sacks":0.00,
    "SackYards":0.00,
    "QuarterbackHits":0.00,
    "PassesDefended":0.00,
    "FumblesForced":0.00,
    "FumblesRecovered":0.00,
    "FumbleReturnYards":0.00,
    "FumbleReturnTouchdowns":0.00,
    "Interceptions":0.00,
    "InterceptionReturnYards":0.00,
    "InterceptionReturnTouchdowns":0.00,
    "BlockedKicks":0.00,
    "SpecialTeamsSoloTackles":0.00,
    "SpecialTeamsAssistedTackles":0.00,
    "MiscSoloTackles":0.00,
    "MiscAssistedTackles":0.00,
    "Punts":0.00,
    "PuntYards":0.00,
    "PuntAverage":0,
    "FieldGoalsAttempted":0.00,
    "FieldGoalsMade":0.00,
    "FieldGoalsLongestMade":0.00,
    "ExtraPointsMade":0.00,
    "TwoPointConversionPasses":0.00,
    "TwoPointConversionRuns":0.00,
    "TwoPointConversionReceptions":0.00,
    "FantasyPoints":50.10,
    "FantasyPointsPPR":76.10,
    "ReceptionPercentage":70.3,
    "ReceivingYardsPerTarget":6.9,
    "Tackles":0,
    "OffensiveTouchdowns":3,
    "DefensiveTouchdowns":0,
    "SpecialTeamsTouchdowns":0,
    "Touchdowns":3,
    "FantasyPosition":"RB",
    "FieldGoalPercentage":0,
    "PlayerSeasonID":15524722,
    "FumblesOwnRecoveries":0.00,
    "FumblesOutOfBounds":0.00,
    "KickReturnFairCatches":0.00,
    "PuntReturnFairCatches":0.00,
    "PuntTouchbacks":0.00,
    "PuntInside20":0.00,
    "PuntNetAverage":0,
    "ExtraPointsAttempted":0.00,
    "BlockedKickReturnTouchdowns":0.00,
    "FieldGoalReturnTouchdowns":0.00,
    "Safeties":0.00,
    "FieldGoalsHadBlocked":0.00,
    "PuntsHadBlocked":0.00,
    "ExtraPointsHadBlocked":0.00,
    "PuntLong":0.00,
    "BlockedKickReturnYards":0.00,
    "FieldGoalReturnYards":0.00,
    "PuntNetYards":0.00,
    "SpecialTeamsFumblesForced":0.00,
    "SpecialTeamsFumblesRecovered":0.00,
    "MiscFumblesForced":0.00,
    "MiscFumblesRecovered":0.00,
    "ShortName":"David Johnson",
    "SafetiesAllowed":0.00,
    "Temperature":71,
    "Humidity":47,
    "WindSpeed":3,
    "OffensiveSnapsPlayed":null,
    "DefensiveSnapsPlayed":null,
    "SpecialTeamsSnapsPlayed":null,
    "OffensiveTeamSnaps":226,
    "DefensiveTeamSnaps":null,
    "SpecialTeamsTeamSnaps":null,
    "AuctionValue":null,
    "AuctionValuePPR":null,
    "TwoPointConversionReturns":0.00,
    "FantasyPointsFanDuel":63.10,
    "FieldGoalsMade0to19":0.00,
    "FieldGoalsMade20to29":0.00,
    "FieldGoalsMade30to39":0.00,
    "FieldGoalsMade40to49":0.00,
    "FieldGoalsMade50Plus":0.00,
    "FantasyPointsDraftKings":77.10,
    "FantasyPointsYahoo":63.10,
    "AverageDraftPosition":null,
    "AverageDraftPositionPPR":null,
    "TeamID":1,
    "GlobalTeamID":1,
    "FantasyPointsFantasyDraft":77.10
  },
  {
    "PlayerID":15010,
    "SeasonType":1,
    "Season":2016,
    "Team":"ARI",
    "Number":33,
    "Name":"Kerwynn Williams",
    "Position":"RB",
    "PositionCategory":"OFF",
    "Activated":10,
    "Played":10,
    "Started":0,
    "PassingAttempts":0.00,
    "PassingCompletions":0.00,
    "PassingYards":0.00,
    "PassingCompletionPercentage":0,
    "PassingYardsPerAttempt":0,
    "PassingYardsPerCompletion":0,
    "PassingTouchdowns":0.00,
    "PassingInterceptions":0.00,
    "PassingRating":0,
    "PassingLong":0.00,
    "PassingSacks":0.00,
    "PassingSackYards":0.00,
    "RushingAttempts":1.00,
    "RushingYards":1.00,
    "RushingYardsPerAttempt":1,
    "RushingTouchdowns":1.00,
    "RushingLong":1.00,
    "ReceivingTargets":0.00,
    "Receptions":0.00,
    "ReceivingYards":0.00,
    "ReceivingYardsPerReception":0,
    "ReceivingTouchdowns":0.00,
    "ReceivingLong":0.00,
    "Fumbles":0.00,
    "FumblesLost":0.00,
    "PuntReturns":0.00,
    "PuntReturnYards":0.00,
    "PuntReturnYardsPerAttempt":0,
    "PuntReturnTouchdowns":0.00,
    "PuntReturnLong":0.00,
    "KickReturns":0.00,
    "KickReturnYards":0.00,
    "KickReturnYardsPerAttempt":0,
    "KickReturnTouchdowns":0.00,
    "KickReturnLong":0.00,
    "SoloTackles":0.00,
    "AssistedTackles":0.00,
    "TacklesForLoss":0.00,
    "Sacks":0.00,
    "SackYards":0.00,
    "QuarterbackHits":0.00,
    "PassesDefended":0.00,
    "FumblesForced":0.00,
    "FumblesRecovered":0.00,
    "FumbleReturnYards":0.00,
    "FumbleReturnTouchdowns":0.00,
    "Interceptions":0.00,
    "InterceptionReturnYards":0.00,
    "InterceptionReturnTouchdowns":0.00,
    "BlockedKicks":0.00,
    "SpecialTeamsSoloTackles":0.00,
    "SpecialTeamsAssistedTackles":0.00,
    "MiscSoloTackles":0.00,
    "MiscAssistedTackles":0.00,
    "Punts":0.00,
    "PuntYards":0.00,
    "PuntAverage":0,
    "FieldGoalsAttempted":0.00,
    "FieldGoalsMade":0.00,
    "FieldGoalsLongestMade":0.00,
    "ExtraPointsMade":0.00,
    "TwoPointConversionPasses":0.00,
    "TwoPointConversionRuns":0.00,
    "TwoPointConversionReceptions":0.00,
    "FantasyPoints":6.10,
    "FantasyPointsPPR":6.10,
    "ReceptionPercentage":0,
    "ReceivingYardsPerTarget":0,
    "Tackles":0,
    "OffensiveTouchdowns":1,
    "DefensiveTouchdowns":0,
    "SpecialTeamsTouchdowns":0,
    "Touchdowns":1,
    "FantasyPosition":"RB",
    "FieldGoalPercentage":0,
    "PlayerSeasonID":162025884,
    "FumblesOwnRecoveries":0.00,
    "FumblesOutOfBounds":0.00,
    "KickReturnFairCatches":0.00,
    "PuntReturnFairCatches":0.00,
    "PuntTouchbacks":0.00,
    "PuntInside20":0.00,
    "PuntNetAverage":0,
    "ExtraPointsAttempted":0.00,
    "BlockedKickReturnTouchdowns":0.00,
    "FieldGoalReturnTouchdowns":0.00,
    "Safeties":0.00,
    "FieldGoalsHadBlocked":0.00,
    "PuntsHadBlocked":0.00,
    "ExtraPointsHadBlocked":0.00,
    "PuntLong":0.00,
    "BlockedKickReturnYards":0.00,
    "FieldGoalReturnYards":0.00,
    "PuntNetYards":0.00,
    "SpecialTeamsFumblesForced":0.00,
    "SpecialTeamsFumblesRecovered":0.00,
    "MiscFumblesForced":0.00,
    "MiscFumblesRecovered":0.00,
    "ShortName":"Kerwynn Williams",
    "SafetiesAllowed":0.00,
    "Temperature":75,
    "Humidity":46,
    "WindSpeed":5,
    "OffensiveSnapsPlayed":null,
    "DefensiveSnapsPlayed":null,
    "SpecialTeamsSnapsPlayed":null,
    "OffensiveTeamSnaps":226,
    "DefensiveTeamSnaps":null,
    "SpecialTeamsTeamSnaps":null,
    "AuctionValue":null,
    "AuctionValuePPR":null,
    "TwoPointConversionReturns":0.00,
    "FantasyPointsFanDuel":6.10,
    "FieldGoalsMade0to19":0.00,
    "FieldGoalsMade20to29":0.00,
    "FieldGoalsMade30to39":0.00,
    "FieldGoalsMade40to49":0.00,
    "FieldGoalsMade50Plus":0.00,
    "FantasyPointsDraftKings":6.10,
    "FantasyPointsYahoo":6.10,
    "AverageDraftPosition":null,
    "AverageDraftPositionPPR":null,
    "TeamID":1,
    "GlobalTeamID":1,
    "FantasyPointsFantasyDraft":6.10
  },
  {
    "PlayerID":15224,
    "SeasonType":1,
    "Season":2016,
    "Team":"ARI",
    "Number":38,
    "Name":"Andre Ellington",
    "Position":"RB",
    "PositionCategory":"OFF",
    "Activated":16,
    "Played":16,
    "Started":0,
    "PassingAttempts":0.00,
    "PassingCompletions":0.00,
    "PassingYards":0.00,
    "PassingCompletionPercentage":0,
    "PassingYardsPerAttempt":0,
    "PassingYardsPerCompletion":0,
    "PassingTouchdowns":0.00,
    "PassingInterceptions":0.00,
    "PassingRating":0,
    "PassingLong":0.00,
    "PassingSacks":0.00,
    "PassingSackYards":0.00,
    "RushingAttempts":4.00,
    "RushingYards":19.00,
    "RushingYardsPerAttempt":4.8,
    "RushingTouchdowns":0.00,
    "RushingLong":8.00,
    "ReceivingTargets":6.00,
    "Receptions":6.00,
    "ReceivingYards":57.00,
    "ReceivingYardsPerReception":9.5,
    "ReceivingTouchdowns":0.00,
    "ReceivingLong":16.00,
    "Fumbles":0.00,
    "FumblesLost":0.00,
    "PuntReturns":0.00,
    "PuntReturnYards":0.00,
    "PuntReturnYardsPerAttempt":0,
    "PuntReturnTouchdowns":0.00,
    "PuntReturnLong":0.00,
    "KickReturns":0.00,
    "KickReturnYards":0.00,
    "KickReturnYardsPerAttempt":0,
    "KickReturnTouchdowns":0.00,
    "KickReturnLong":0.00,
    "SoloTackles":0.00,
    "AssistedTackles":0.00,
    "TacklesForLoss":0.00,
    "Sacks":0.00,
    "SackYards":0.00,
    "QuarterbackHits":0.00,
    "PassesDefended":0.00,
    "FumblesForced":0.00,
    "FumblesRecovered":0.00,
    "FumbleReturnYards":0.00,
    "FumbleReturnTouchdowns":0.00,
    "Interceptions":0.00,
    "InterceptionReturnYards":0.00,
    "InterceptionReturnTouchdowns":0.00,
    "BlockedKicks":0.00,
    "SpecialTeamsSoloTackles":0.00,
    "SpecialTeamsAssistedTackles":0.00,
    "MiscSoloTackles":0.00,
    "MiscAssistedTackles":0.00,
    "Punts":0.00,
    "PuntYards":0.00,
    "PuntAverage":0,
    "FieldGoalsAttempted":0.00,
    "FieldGoalsMade":0.00,
    "FieldGoalsLongestMade":0.00,
    "ExtraPointsMade":0.00,
    "TwoPointConversionPasses":0.00,
    "TwoPointConversionRuns":0.00,
    "TwoPointConversionReceptions":0.00,
    "FantasyPoints":7.60,
    "FantasyPointsPPR":13.60,
    "ReceptionPercentage":100,
    "ReceivingYardsPerTarget":9.5,
    "Tackles":0,
    "OffensiveTouchdowns":0,
    "DefensiveTouchdowns":0,
    "SpecialTeamsTouchdowns":0,
    "Touchdowns":0,
    "FantasyPosition":"RB",
    "FieldGoalPercentage":0,
    "PlayerSeasonID":15524712,
    "FumblesOwnRecoveries":0.00,
    "FumblesOutOfBounds":0.00,
    "KickReturnFairCatches":0.00,
    "PuntReturnFairCatches":0.00,
    "PuntTouchbacks":0.00,
    "PuntInside20":0.00,
    "PuntNetAverage":0,
    "ExtraPointsAttempted":0.00,
    "BlockedKickReturnTouchdowns":0.00,
    "FieldGoalReturnTouchdowns":0.00,
    "Safeties":0.00,
    "FieldGoalsHadBlocked":0.00,
    "PuntsHadBlocked":0.00,
    "ExtraPointsHadBlocked":0.00,
    "PuntLong":0.00,
    "BlockedKickReturnYards":0.00,
    "FieldGoalReturnYards":0.00,
    "PuntNetYards":0.00,
    "SpecialTeamsFumblesForced":0.00,
    "SpecialTeamsFumblesRecovered":0.00,
    "MiscFumblesForced":0.00,
    "MiscFumblesRecovered":0.00,
    "ShortName":"Andre Ellington",
    "SafetiesAllowed":0.00,
    "Temperature":71,
    "Humidity":47,
    "WindSpeed":3,
    "OffensiveSnapsPlayed":null,
    "DefensiveSnapsPlayed":null,
    "SpecialTeamsSnapsPlayed":null,
    "OffensiveTeamSnaps":226,
    "DefensiveTeamSnaps":null,
    "SpecialTeamsTeamSnaps":null,
    "AuctionValue":null,
    "AuctionValuePPR":null,
    "TwoPointConversionReturns":0.00,
    "FantasyPointsFanDuel":10.60,
    "FieldGoalsMade0to19":0.00,
    "FieldGoalsMade20to29":0.00,
    "FieldGoalsMade30to39":0.00,
    "FieldGoalsMade40to49":0.00,
    "FieldGoalsMade50Plus":0.00,
    "FantasyPointsDraftKings":13.60,
    "FantasyPointsYahoo":10.60,
    "AverageDraftPosition":null,
    "AverageDraftPositionPPR":null,
    "TeamID":1,
    "GlobalTeamID":1,
    "FantasyPointsFantasyDraft":13.60
  },
  {
    "PlayerID":14847,
    "SeasonType":1,
    "Season":2016,
    "Team":"ARI",
    "Number":80,
    "Name":"Ifeanyi Momah",
    "Position":"WR",
    "PositionCategory":"OFF",
    "Activated":5,
    "Played":5,
    "Started":1,
    "PassingAttempts":0.00,
    "PassingCompletions":0.00,
    "PassingYards":0.00,
    "PassingCompletionPercentage":0,
    "PassingYardsPerAttempt":0,
    "PassingYardsPerCompletion":0,
    "PassingTouchdowns":0.00,
    "PassingInterceptions":0.00,
    "PassingRating":0,
    "PassingLong":0.00,
    "PassingSacks":0.00,
    "PassingSackYards":0.00,
    "RushingAttempts":0.00,
    "RushingYards":0.00,
    "RushingYardsPerAttempt":0,
    "RushingTouchdowns":0.00,
    "RushingLong":0.00,
    "ReceivingTargets":1.00,
    "Receptions":1.00,
    "ReceivingYards":23.00,
    "ReceivingYardsPerReception":23,
    "ReceivingTouchdowns":0.00,
    "ReceivingLong":23.00,
    "Fumbles":0.00,
    "FumblesLost":0.00,
    "PuntReturns":0.00,
    "PuntReturnYards":0.00,
    "PuntReturnYardsPerAttempt":0,
    "PuntReturnTouchdowns":0.00,
    "PuntReturnLong":0.00,
    "KickReturns":0.00,
    "KickReturnYards":0.00,
    "KickReturnYardsPerAttempt":0,
    "KickReturnTouchdowns":0.00,
    "KickReturnLong":0.00,
    "SoloTackles":0.00,
    "AssistedTackles":0.00,
    "TacklesForLoss":0.00,
    "Sacks":0.00,
    "SackYards":0.00,
    "QuarterbackHits":0.00,
    "PassesDefended":0.00,
    "FumblesForced":0.00,
    "FumblesRecovered":0.00,
    "FumbleReturnYards":0.00,
    "FumbleReturnTouchdowns":0.00,
    "Interceptions":0.00,
    "InterceptionReturnYards":0.00,
    "InterceptionReturnTouchdowns":0.00,
    "BlockedKicks":0.00,
    "SpecialTeamsSoloTackles":0.00,
    "SpecialTeamsAssistedTackles":0.00,
    "MiscSoloTackles":0.00,
    "MiscAssistedTackles":0.00,
    "Punts":0.00,
    "PuntYards":0.00,
    "PuntAverage":0,
    "FieldGoalsAttempted":0.00,
    "FieldGoalsMade":0.00,
    "FieldGoalsLongestMade":0.00,
    "ExtraPointsMade":0.00,
    "TwoPointConversionPasses":0.00,
    "TwoPointConversionRuns":0.00,
    "TwoPointConversionReceptions":0.00,
    "FantasyPoints":2.30,
    "FantasyPointsPPR":3.30,
    "ReceptionPercentage":100,
    "ReceivingYardsPerTarget":23,
    "Tackles":0,
    "OffensiveTouchdowns":0,
    "DefensiveTouchdowns":0,
    "SpecialTeamsTouchdowns":0,
    "Touchdowns":0,
    "FantasyPosition":"WR",
    "FieldGoalPercentage":0,
    "PlayerSeasonID":162024697,
    "FumblesOwnRecoveries":0.00,
    "FumblesOutOfBounds":0.00,
    "KickReturnFairCatches":0.00,
    "PuntReturnFairCatches":0.00,
    "PuntTouchbacks":0.00,
    "PuntInside20":0.00,
    "PuntNetAverage":0,
    "ExtraPointsAttempted":0.00,
    "BlockedKickReturnTouchdowns":0.00,
    "FieldGoalReturnTouchdowns":0.00,
    "Safeties":0.00,
    "FieldGoalsHadBlocked":0.00,
    "PuntsHadBlocked":0.00,
    "ExtraPointsHadBlocked":0.00,
    "PuntLong":0.00,
    "BlockedKickReturnYards":0.00,
    "FieldGoalReturnYards":0.00,
    "PuntNetYards":0.00,
    "SpecialTeamsFumblesForced":0.00,
    "SpecialTeamsFumblesRecovered":0.00,
    "MiscFumblesForced":0.00,
    "MiscFumblesRecovered":0.00,
    "ShortName":"Ifeanyi Momah",
    "SafetiesAllowed":0.00,
    "Temperature":74,
    "Humidity":47,
    "WindSpeed":4,
    "OffensiveSnapsPlayed":null,
    "DefensiveSnapsPlayed":null,
    "SpecialTeamsSnapsPlayed":null,
    "OffensiveTeamSnaps":226,
    "DefensiveTeamSnaps":null,
    "SpecialTeamsTeamSnaps":null,
    "AuctionValue":null,
    "AuctionValuePPR":null,
    "TwoPointConversionReturns":0.00,
    "FantasyPointsFanDuel":2.80,
    "FieldGoalsMade0to19":0.00,
    "FieldGoalsMade20to29":0.00,
    "FieldGoalsMade30to39":0.00,
    "FieldGoalsMade40to49":0.00,
    "FieldGoalsMade50Plus":0.00,
    "FantasyPointsDraftKings":3.30,
    "FantasyPointsYahoo":2.80,
    "AverageDraftPosition":null,
    "AverageDraftPositionPPR":null,
    "TeamID":1,
    "GlobalTeamID":1,
    "FantasyPointsFantasyDraft":3.30
  },
  {
    "PlayerID":11026,
    "SeasonType":1,
    "Season":2016,
    "Team":"ARI",
    "Number":84,
    "Name":"Jermaine Gresham",
    "Position":"TE",
    "PositionCategory":"OFF",
    "Activated":16,
    "Played":16,
    "Started":14,
    "PassingAttempts":0.00,
    "PassingCompletions":0.00,
    "PassingYards":0.00,
    "PassingCompletionPercentage":0,
    "PassingYardsPerAttempt":0,
    "PassingYardsPerCompletion":0,
    "PassingTouchdowns":0.00,
    "PassingInterceptions":0.00,
    "PassingRating":0,
    "PassingLong":0.00,
    "PassingSacks":0.00,
    "PassingSackYards":0.00,
    "RushingAttempts":0.00,
    "RushingYards":0.00,
    "RushingYardsPerAttempt":0,
    "RushingTouchdowns":0.00,
    "RushingLong":0.00,
    "ReceivingTargets":8.00,
    "Receptions":4.00,
    "ReceivingYards":50.00,
    "ReceivingYardsPerReception":12.5,
    "ReceivingTouchdowns":0.00,
    "ReceivingLong":20.00,
    "Fumbles":0.00,
    "FumblesLost":0.00,
    "PuntReturns":0.00,
    "PuntReturnYards":0.00,
    "PuntReturnYardsPerAttempt":0,
    "PuntReturnTouchdowns":0.00,
    "PuntReturnLong":0.00,
    "KickReturns":0.00,
    "KickReturnYards":0.00,
    "KickReturnYardsPerAttempt":0,
    "KickReturnTouchdowns":0.00,
    "KickReturnLong":0.00,
    "SoloTackles":0.00,
    "AssistedTackles":0.00,
    "TacklesForLoss":0.00,
    "Sacks":0.00,
    "SackYards":0.00,
    "QuarterbackHits":0.00,
    "PassesDefended":0.00,
    "FumblesForced":0.00,
    "FumblesRecovered":0.00,
    "FumbleReturnYards":0.00,
    "FumbleReturnTouchdowns":0.00,
    "Interceptions":0.00,
    "InterceptionReturnYards":0.00,
    "InterceptionReturnTouchdowns":0.00,
    "BlockedKicks":0.00,
    "SpecialTeamsSoloTackles":0.00,
    "SpecialTeamsAssistedTackles":0.00,
    "MiscSoloTackles":0.00,
    "MiscAssistedTackles":0.00,
    "Punts":0.00,
    "PuntYards":0.00,
    "PuntAverage":0,
    "FieldGoalsAttempted":0.00,
    "FieldGoalsMade":0.00,
    "FieldGoalsLongestMade":0.00,
    "ExtraPointsMade":0.00,
    "TwoPointConversionPasses":0.00,
    "TwoPointConversionRuns":0.00,
    "TwoPointConversionReceptions":0.00,
    "FantasyPoints":5.00,
    "FantasyPointsPPR":9.00,
    "ReceptionPercentage":50.0,
    "ReceivingYardsPerTarget":6.2,
    "Tackles":0,
    "OffensiveTouchdowns":0,
    "DefensiveTouchdowns":0,
    "SpecialTeamsTouchdowns":0,
    "Touchdowns":0,
    "FantasyPosition":"TE",
    "FieldGoalPercentage":0,
    "PlayerSeasonID":15524621,
    "FumblesOwnRecoveries":0.00,
    "FumblesOutOfBounds":0.00,
    "KickReturnFairCatches":0.00,
    "PuntReturnFairCatches":0.00,
    "PuntTouchbacks":0.00,
    "PuntInside20":0.00,
    "PuntNetAverage":0,
    "ExtraPointsAttempted":0.00,
    "BlockedKickReturnTouchdowns":0.00,
    "FieldGoalReturnTouchdowns":0.00,
    "Safeties":0.00,
    "FieldGoalsHadBlocked":0.00,
    "PuntsHadBlocked":0.00,
    "ExtraPointsHadBlocked":0.00,
    "PuntLong":0.00,
    "BlockedKickReturnYards":0.00,
    "FieldGoalReturnYards":0.00,
    "PuntNetYards":0.00,
    "SpecialTeamsFumblesForced":0.00,
    "SpecialTeamsFumblesRecovered":0.00,
    "MiscFumblesForced":0.00,
    "MiscFumblesRecovered":0.00,
    "ShortName":"Jermaine Gresham",
    "SafetiesAllowed":0.00,
    "Temperature":71,
    "Humidity":47,
    "WindSpeed":3,
    "OffensiveSnapsPlayed":null,
    "DefensiveSnapsPlayed":null,
    "SpecialTeamsSnapsPlayed":null,
    "OffensiveTeamSnaps":226,
    "DefensiveTeamSnaps":null,
    "SpecialTeamsTeamSnaps":null,
    "AuctionValue":null,
    "AuctionValuePPR":null,
    "TwoPointConversionReturns":0.00,
    "FantasyPointsFanDuel":7.00,
    "FieldGoalsMade0to19":0.00,
    "FieldGoalsMade20to29":0.00,
    "FieldGoalsMade30to39":0.00,
    "FieldGoalsMade40to49":0.00,
    "FieldGoalsMade50Plus":0.00,
    "FantasyPointsDraftKings":9.00,
    "FantasyPointsYahoo":7.00,
    "AverageDraftPosition":null,
    "AverageDraftPositionPPR":null,
    "TeamID":1,
    "GlobalTeamID":1,
    "FantasyPointsFantasyDraft":9.00
  },
  {
    "PlayerID":15247,
    "SeasonType":1,
    "Season":2016,
    "Team":"ARI",
    "Number":85,
    "Name":"Darren Fells",
    "Position":"TE",
    "PositionCategory":"OFF",
    "Activated":14,
    "Played":14,
    "Started":7,
    "PassingAttempts":0.00,
    "PassingCompletions":0.00,
    "PassingYards":0.00,
    "PassingCompletionPercentage":0,
    "PassingYardsPerAttempt":0,
    "PassingYardsPerCompletion":0,
    "PassingTouchdowns":0.00,
    "PassingInterceptions":0.00,
    "PassingRating":0,
    "PassingLong":0.00,
    "PassingSacks":0.00,
    "PassingSackYards":0.00,
    "RushingAttempts":0.00,
    "RushingYards":0.00,
    "RushingYardsPerAttempt":0,
    "RushingTouchdowns":0.00,
    "RushingLong":0.00,
    "ReceivingTargets":7.00,
    "Receptions":5.00,
    "ReceivingYards":42.00,
    "ReceivingYardsPerReception":8.4,
    "ReceivingTouchdowns":0.00,
    "ReceivingLong":12.00,
    "Fumbles":0.00,
    "FumblesLost":0.00,
    "PuntReturns":0.00,
    "PuntReturnYards":0.00,
    "PuntReturnYardsPerAttempt":0,
    "PuntReturnTouchdowns":0.00,
    "PuntReturnLong":0.00,
    "KickReturns":0.00,
    "KickReturnYards":0.00,
    "KickReturnYardsPerAttempt":0,
    "KickReturnTouchdowns":0.00,
    "KickReturnLong":0.00,
    "SoloTackles":0.00,
    "AssistedTackles":0.00,
    "TacklesForLoss":0.00,
    "Sacks":0.00,
    "SackYards":0.00,
    "QuarterbackHits":0.00,
    "PassesDefended":0.00,
    "FumblesForced":0.00,
    "FumblesRecovered":0.00,
    "FumbleReturnYards":0.00,
    "FumbleReturnTouchdowns":0.00,
    "Interceptions":0.00,
    "InterceptionReturnYards":0.00,
    "InterceptionReturnTouchdowns":0.00,
    "BlockedKicks":0.00,
    "SpecialTeamsSoloTackles":0.00,
    "SpecialTeamsAssistedTackles":0.00,
    "MiscSoloTackles":0.00,
    "MiscAssistedTackles":0.00,
    "Punts":0.00,
    "PuntYards":0.00,
    "PuntAverage":0,
    "FieldGoalsAttempted":0.00,
    "FieldGoalsMade":0.00,
    "FieldGoalsLongestMade":0.00,
    "ExtraPointsMade":0.00,
    "TwoPointConversionPasses":0.00,
    "TwoPointConversionRuns":0.00,
    "TwoPointConversionReceptions":0.00,
    "FantasyPoints":4.20,
    "FantasyPointsPPR":9.20,
    "ReceptionPercentage":71.4,
    "ReceivingYardsPerTarget":6,
    "Tackles":0,
    "OffensiveTouchdowns":0,
    "DefensiveTouchdowns":0,
    "SpecialTeamsTouchdowns":0,
    "Touchdowns":0,
    "FantasyPosition":"TE",
    "FieldGoalPercentage":0,
    "PlayerSeasonID":15524634,
    "FumblesOwnRecoveries":0.00,
    "FumblesOutOfBounds":0.00,
    "KickReturnFairCatches":0.00,
    "PuntReturnFairCatches":0.00,
    "PuntTouchbacks":0.00,
    "PuntInside20":0.00,
    "PuntNetAverage":0,
    "ExtraPointsAttempted":0.00,
    "BlockedKickReturnTouchdowns":0.00,
    "FieldGoalReturnTouchdowns":0.00,
    "Safeties":0.00,
    "FieldGoalsHadBlocked":0.00,
    "PuntsHadBlocked":0.00,
    "ExtraPointsHadBlocked":0.00,
    "PuntLong":0.00,
    "BlockedKickReturnYards":0.00,
    "FieldGoalReturnYards":0.00,
    "PuntNetYards":0.00,
    "SpecialTeamsFumblesForced":0.00,
    "SpecialTeamsFumblesRecovered":0.00,
    "MiscFumblesForced":0.00,
    "MiscFumblesRecovered":0.00,
    "ShortName":"Darren Fells",
    "SafetiesAllowed":0.00,
    "Temperature":71,
    "Humidity":47,
    "WindSpeed":3,
    "OffensiveSnapsPlayed":null,
    "DefensiveSnapsPlayed":null,
    "SpecialTeamsSnapsPlayed":null,
    "OffensiveTeamSnaps":226,
    "DefensiveTeamSnaps":null,
    "SpecialTeamsTeamSnaps":null,
    "AuctionValue":null,
    "AuctionValuePPR":null,
    "TwoPointConversionReturns":0.00,
    "FantasyPointsFanDuel":6.70,
    "FieldGoalsMade0to19":0.00,
    "FieldGoalsMade20to29":0.00,
    "FieldGoalsMade30to39":0.00,
    "FieldGoalsMade40to49":0.00,
    "FieldGoalsMade50Plus":0.00,
    "FantasyPointsDraftKings":9.20,
    "FantasyPointsYahoo":6.70,
    "AverageDraftPosition":null,
    "AverageDraftPositionPPR":null,
    "TeamID":1,
    "GlobalTeamID":1,
    "FantasyPointsFantasyDraft":9.20
  },
  {
    "PlayerID":16648,
    "SeasonType":1,
    "Season":2016,
    "Team":"ARI",
    "Number":87,
    "Name":"Troy Niklas",
    "Position":"TE",
    "PositionCategory":"OFF",
    "Activated":3,
    "Played":3,
    "Started":2,
    "PassingAttempts":0.00,
    "PassingCompletions":0.00,
    "PassingYards":0.00,
    "PassingCompletionPercentage":0,
    "PassingYardsPerAttempt":0,
    "PassingYardsPerCompletion":0,
    "PassingTouchdowns":0.00,
    "PassingInterceptions":0.00,
    "PassingRating":0,
    "PassingLong":null,
    "PassingSacks":0.00,
    "PassingSackYards":0.00,
    "RushingAttempts":0.00,
    "RushingYards":0.00,
    "RushingYardsPerAttempt":0,
    "RushingTouchdowns":0.00,
    "RushingLong":null,
    "ReceivingTargets":0.00,
    "Receptions":0.00,
    "ReceivingYards":0.00,
    "ReceivingYardsPerReception":0,
    "ReceivingTouchdowns":0.00,
    "ReceivingLong":null,
    "Fumbles":0.00,
    "FumblesLost":0.00,
    "PuntReturns":0.00,
    "PuntReturnYards":0.00,
    "PuntReturnYardsPerAttempt":0,
    "PuntReturnTouchdowns":0.00,
    "PuntReturnLong":null,
    "KickReturns":0.00,
    "KickReturnYards":0.00,
    "KickReturnYardsPerAttempt":0,
    "KickReturnTouchdowns":0.00,
    "KickReturnLong":null,
    "SoloTackles":0.00,
    "AssistedTackles":0.00,
    "TacklesForLoss":0.00,
    "Sacks":0.00,
    "SackYards":0.00,
    "QuarterbackHits":0.00,
    "PassesDefended":0.00,
    "FumblesForced":0.00,
    "FumblesRecovered":0.00,
    "FumbleReturnYards":0.00,
    "FumbleReturnTouchdowns":0.00,
    "Interceptions":0.00,
    "InterceptionReturnYards":0.00,
    "InterceptionReturnTouchdowns":0.00,
    "BlockedKicks":0.00,
    "SpecialTeamsSoloTackles":0.00,
    "SpecialTeamsAssistedTackles":0.00,
    "MiscSoloTackles":0.00,
    "MiscAssistedTackles":0.00,
    "Punts":0.00,
    "PuntYards":0.00,
    "PuntAverage":0,
    "FieldGoalsAttempted":0.00,
    "FieldGoalsMade":0.00,
    "FieldGoalsLongestMade":null,
    "ExtraPointsMade":0.00,
    "TwoPointConversionPasses":0.00,
    "TwoPointConversionRuns":0.00,
    "TwoPointConversionReceptions":0.00,
    "FantasyPoints":0.00,
    "FantasyPointsPPR":0.00,
    "ReceptionPercentage":0,
    "ReceivingYardsPerTarget":0,
    "Tackles":0,
    "OffensiveTouchdowns":0,
    "DefensiveTouchdowns":0,
    "SpecialTeamsTouchdowns":0,
    "Touchdowns":0,
    "FantasyPosition":"TE",
    "FieldGoalPercentage":0,
    "PlayerSeasonID":15524647,
    "FumblesOwnRecoveries":0.00,
    "FumblesOutOfBounds":0.00,
    "KickReturnFairCatches":0.00,
    "PuntReturnFairCatches":0.00,
    "PuntTouchbacks":0.00,
    "PuntInside20":0.00,
    "PuntNetAverage":0,
    "ExtraPointsAttempted":0.00,
    "BlockedKickReturnTouchdowns":0.00,
    "FieldGoalReturnTouchdowns":0.00,
    "Safeties":0.00,
    "FieldGoalsHadBlocked":0.00,
    "PuntsHadBlocked":0.00,
    "ExtraPointsHadBlocked":0.00,
    "PuntLong":null,
    "BlockedKickReturnYards":0.00,
    "FieldGoalReturnYards":0.00,
    "PuntNetYards":0.00,
    "SpecialTeamsFumblesForced":0.00,
    "SpecialTeamsFumblesRecovered":0.00,
    "MiscFumblesForced":0.00,
    "MiscFumblesRecovered":0.00,
    "ShortName":"Troy Niklas",
    "SafetiesAllowed":0.00,
    "Temperature":71,
    "Humidity":47,
    "WindSpeed":3,
    "OffensiveSnapsPlayed":null,
    "DefensiveSnapsPlayed":null,
    "SpecialTeamsSnapsPlayed":null,
    "OffensiveTeamSnaps":226,
    "DefensiveTeamSnaps":null,
    "SpecialTeamsTeamSnaps":null,
    "AuctionValue":null,
    "AuctionValuePPR":null,
    "TwoPointConversionReturns":0.00,
    "FantasyPointsFanDuel":0.00,
    "FieldGoalsMade0to19":0.00,
    "FieldGoalsMade20to29":0.00,
    "FieldGoalsMade30to39":0.00,
    "FieldGoalsMade40to49":0.00,
    "FieldGoalsMade50Plus":0.00,
    "FantasyPointsDraftKings":0.00,
    "FantasyPointsYahoo":0.00,
    "AverageDraftPosition":null,
    "AverageDraftPositionPPR":null,
    "TeamID":1,
    "GlobalTeamID":1,
    "FantasyPointsFantasyDraft":0.00
  },
  {
    "PlayerID":18399,
    "SeasonType":1,
    "Season":2016,
    "Team":"ARI",
    "Number":89,
    "Name":"Hakeem Valles",
    "Position":"TE",
    "PositionCategory":"OFF",
    "Activated":11,
    "Played":11,
    "Started":1,
    "PassingAttempts":0.00,
    "PassingCompletions":0.00,
    "PassingYards":0.00,
    "PassingCompletionPercentage":0,
    "PassingYardsPerAttempt":0,
    "PassingYardsPerCompletion":0,
    "PassingTouchdowns":0.00,
    "PassingInterceptions":0.00,
    "PassingRating":0,
    "PassingLong":null,
    "PassingSacks":0.00,
    "PassingSackYards":0.00,
    "RushingAttempts":0.00,
    "RushingYards":0.00,
    "RushingYardsPerAttempt":0,
    "RushingTouchdowns":0.00,
    "RushingLong":null,
    "ReceivingTargets":0.00,
    "Receptions":0.00,
    "ReceivingYards":0.00,
    "ReceivingYardsPerReception":0,
    "ReceivingTouchdowns":0.00,
    "ReceivingLong":null,
    "Fumbles":0.00,
    "FumblesLost":0.00,
    "PuntReturns":0.00,
    "PuntReturnYards":0.00,
    "PuntReturnYardsPerAttempt":0,
    "PuntReturnTouchdowns":0.00,
    "PuntReturnLong":null,
    "KickReturns":0.00,
    "KickReturnYards":0.00,
    "KickReturnYardsPerAttempt":0,
    "KickReturnTouchdowns":0.00,
    "KickReturnLong":null,
    "SoloTackles":0.00,
    "AssistedTackles":0.00,
    "TacklesForLoss":0.00,
    "Sacks":0.00,
    "SackYards":0.00,
    "QuarterbackHits":0.00,
    "PassesDefended":0.00,
    "FumblesForced":0.00,
    "FumblesRecovered":0.00,
    "FumbleReturnYards":0.00,
    "FumbleReturnTouchdowns":0.00,
    "Interceptions":0.00,
    "InterceptionReturnYards":0.00,
    "InterceptionReturnTouchdowns":0.00,
    "BlockedKicks":0.00,
    "SpecialTeamsSoloTackles":0.00,
    "SpecialTeamsAssistedTackles":0.00,
    "MiscSoloTackles":0.00,
    "MiscAssistedTackles":0.00,
    "Punts":0.00,
    "PuntYards":0.00,
    "PuntAverage":0,
    "FieldGoalsAttempted":0.00,
    "FieldGoalsMade":0.00,
    "FieldGoalsLongestMade":null,
    "ExtraPointsMade":0.00,
    "TwoPointConversionPasses":0.00,
    "TwoPointConversionRuns":0.00,
    "TwoPointConversionReceptions":0.00,
    "FantasyPoints":0.00,
    "FantasyPointsPPR":0.00,
    "ReceptionPercentage":0,
    "ReceivingYardsPerTarget":0,
    "Tackles":0,
    "OffensiveTouchdowns":0,
    "DefensiveTouchdowns":0,
    "SpecialTeamsTouchdowns":0,
    "Touchdowns":0,
    "FantasyPosition":"TE",
    "FieldGoalPercentage":0,
    "PlayerSeasonID":162025882,
    "FumblesOwnRecoveries":0.00,
    "FumblesOutOfBounds":0.00,
    "KickReturnFairCatches":0.00,
    "PuntReturnFairCatches":0.00,
    "PuntTouchbacks":0.00,
    "PuntInside20":0.00,
    "PuntNetAverage":0,
    "ExtraPointsAttempted":0.00,
    "BlockedKickReturnTouchdowns":0.00,
    "FieldGoalReturnTouchdowns":0.00,
    "Safeties":0.00,
    "FieldGoalsHadBlocked":0.00,
    "PuntsHadBlocked":0.00,
    "ExtraPointsHadBlocked":0.00,
    "PuntLong":null,
    "BlockedKickReturnYards":0.00,
    "FieldGoalReturnYards":0.00,
    "PuntNetYards":0.00,
    "SpecialTeamsFumblesForced":0.00,
    "SpecialTeamsFumblesRecovered":0.00,
    "MiscFumblesForced":0.00,
    "MiscFumblesRecovered":0.00,
    "ShortName":"Hakeem Valles",
    "SafetiesAllowed":0.00,
    "Temperature":75,
    "Humidity":46,
    "WindSpeed":5,
    "OffensiveSnapsPlayed":null,
    "DefensiveSnapsPlayed":null,
    "SpecialTeamsSnapsPlayed":null,
    "OffensiveTeamSnaps":226,
    "DefensiveTeamSnaps":null,
    "SpecialTeamsTeamSnaps":null,
    "AuctionValue":null,
    "AuctionValuePPR":null,
    "TwoPointConversionReturns":0.00,
    "FantasyPointsFanDuel":0.00,
    "FieldGoalsMade0to19":0.00,
    "FieldGoalsMade20to29":0.00,
    "FieldGoalsMade30to39":0.00,
    "FieldGoalsMade40to49":0.00,
    "FieldGoalsMade50Plus":0.00,
    "FantasyPointsDraftKings":0.00,
    "FantasyPointsYahoo":0.00,
    "AverageDraftPosition":null,
    "AverageDraftPositionPPR":null,
    "TeamID":1,
    "GlobalTeamID":1,
    "FantasyPointsFantasyDraft":0.00
  }
]